{"Tujian":
[
	{"id":1001000, "pokedex_level":0, "levelmax":0, "pokedex_id":1001, "hero_id":[[10042,1],[10016,1]], "consume":[], "achievement_point":25, "target1":1, "attribute1":[[6,60]], "target2":"", "attribute2":[]},
	{"id":1001001, "pokedex_level":1, "levelmax":6, "pokedex_id":1001, "hero_id":[[10042,1],[10016,1]], "consume":[[2,2,2500],[201,432004,2]], "achievement_point":0, "target1":1, "attribute1":[[6,96]], "target2":"", "attribute2":[]},
	{"id":1001002, "pokedex_level":2, "levelmax":6, "pokedex_id":1001, "hero_id":[[10042,1],[10016,1]], "consume":[[2,2,2500],[201,432004,2]], "achievement_point":0, "target1":1, "attribute1":[[6,132]], "target2":"", "attribute2":[]},
	{"id":1001003, "pokedex_level":3, "levelmax":6, "pokedex_id":1001, "hero_id":[[10042,1],[10016,1]], "consume":[[2,2,2500],[201,432004,4]], "achievement_point":0, "target1":1, "attribute1":[[6,168]], "target2":"", "attribute2":[]},
	{"id":1001004, "pokedex_level":4, "levelmax":6, "pokedex_id":1001, "hero_id":[[10042,1],[10016,1]], "consume":[[2,2,2500],[201,432004,4]], "achievement_point":0, "target1":1, "attribute1":[[6,204]], "target2":"", "attribute2":[]},
	{"id":1001005, "pokedex_level":5, "levelmax":6, "pokedex_id":1001, "hero_id":[[10042,1],[10016,1]], "consume":[[2,2,2500],[201,432004,6]], "achievement_point":0, "target1":1, "attribute1":[[6,240]], "target2":"", "attribute2":[]},
	{"id":1001006, "pokedex_level":6, "levelmax":6, "pokedex_id":1001, "hero_id":[[10042,1],[10016,1]], "consume":[[2,2,10000],[201,432004,6]], "achievement_point":20, "target1":1, "attribute1":[[6,300]], "target2":"", "attribute2":[]},
	{"id":1001007, "pokedex_level":7, "levelmax":12, "pokedex_id":1001, "hero_id":[[10042,2],[10016,2]], "consume":[[2,2,5000],[201,432004,9]], "achievement_point":0, "target1":1, "attribute1":[[6,347]], "target2":"", "attribute2":[]},
	{"id":1001008, "pokedex_level":8, "levelmax":12, "pokedex_id":1001, "hero_id":[[10042,2],[10016,2]], "consume":[[2,2,5000],[201,432004,9]], "achievement_point":0, "target1":1, "attribute1":[[6,394]], "target2":"", "attribute2":[]},
	{"id":1001009, "pokedex_level":9, "levelmax":12, "pokedex_id":1001, "hero_id":[[10042,2],[10016,2]], "consume":[[2,2,5000],[201,432004,12]], "achievement_point":0, "target1":1, "attribute1":[[6,440]], "target2":"", "attribute2":[]},
	{"id":1001010, "pokedex_level":10, "levelmax":12, "pokedex_id":1001, "hero_id":[[10042,2],[10016,2]], "consume":[[2,2,5000],[201,432004,12]], "achievement_point":0, "target1":1, "attribute1":[[6,487]], "target2":"", "attribute2":[]},
	{"id":1001011, "pokedex_level":11, "levelmax":12, "pokedex_id":1001, "hero_id":[[10042,2],[10016,2]], "consume":[[2,2,5000],[201,432004,15]], "achievement_point":0, "target1":1, "attribute1":[[6,534]], "target2":"", "attribute2":[]},
	{"id":1001012, "pokedex_level":12, "levelmax":12, "pokedex_id":1001, "hero_id":[[10042,2],[10016,2]], "consume":[[2,2,20000],[201,432004,15]], "achievement_point":20, "target1":1, "attribute1":[[6,612]], "target2":"", "attribute2":[]},
	{"id":1001013, "pokedex_level":13, "levelmax":18, "pokedex_id":1001, "hero_id":[[10042,3],[10016,3]], "consume":[[2,2,10000],[201,432004,20]], "achievement_point":0, "target1":1, "attribute1":[[6,677]], "target2":"", "attribute2":[]},
	{"id":1001014, "pokedex_level":14, "levelmax":18, "pokedex_id":1001, "hero_id":[[10042,3],[10016,3]], "consume":[[2,2,10000],[201,432004,20]], "achievement_point":0, "target1":1, "attribute1":[[6,742]], "target2":"", "attribute2":[]},
	{"id":1001015, "pokedex_level":15, "levelmax":18, "pokedex_id":1001, "hero_id":[[10042,3],[10016,3]], "consume":[[2,2,10000],[201,432004,25]], "achievement_point":0, "target1":1, "attribute1":[[6,806]], "target2":"", "attribute2":[]},
	{"id":1001016, "pokedex_level":16, "levelmax":18, "pokedex_id":1001, "hero_id":[[10042,3],[10016,3]], "consume":[[2,2,10000],[201,432004,25]], "achievement_point":0, "target1":1, "attribute1":[[6,871]], "target2":"", "attribute2":[]},
	{"id":1001017, "pokedex_level":17, "levelmax":18, "pokedex_id":1001, "hero_id":[[10042,3],[10016,3]], "consume":[[2,2,10000],[201,432004,30]], "achievement_point":0, "target1":1, "attribute1":[[6,936]], "target2":"", "attribute2":[]},
	{"id":1001018, "pokedex_level":18, "levelmax":18, "pokedex_id":1001, "hero_id":[[10042,3],[10016,3]], "consume":[[2,2,50000],[201,432004,30]], "achievement_point":20, "target1":1, "attribute1":[[6,1044]], "target2":"", "attribute2":[]},
	{"id":1001019, "pokedex_level":19, "levelmax":24, "pokedex_id":1001, "hero_id":[[10042,4],[10016,4]], "consume":[[2,2,20000],[201,432004,35]], "achievement_point":0, "target1":1, "attribute1":[[6,1134]], "target2":"", "attribute2":[]},
	{"id":1001020, "pokedex_level":20, "levelmax":24, "pokedex_id":1001, "hero_id":[[10042,4],[10016,4]], "consume":[[2,2,20000],[201,432004,35]], "achievement_point":0, "target1":1, "attribute1":[[6,1224]], "target2":"", "attribute2":[]},
	{"id":1001021, "pokedex_level":21, "levelmax":24, "pokedex_id":1001, "hero_id":[[10042,4],[10016,4]], "consume":[[2,2,20000],[201,432004,40]], "achievement_point":0, "target1":1, "attribute1":[[6,1314]], "target2":"", "attribute2":[]},
	{"id":1001022, "pokedex_level":22, "levelmax":24, "pokedex_id":1001, "hero_id":[[10042,4],[10016,4]], "consume":[[2,2,20000],[201,432004,40]], "achievement_point":0, "target1":1, "attribute1":[[6,1404]], "target2":"", "attribute2":[]},
	{"id":1001023, "pokedex_level":23, "levelmax":24, "pokedex_id":1001, "hero_id":[[10042,4],[10016,4]], "consume":[[2,2,20000],[201,432004,45]], "achievement_point":0, "target1":1, "attribute1":[[6,1494]], "target2":"", "attribute2":[]},
	{"id":1001024, "pokedex_level":24, "levelmax":24, "pokedex_id":1001, "hero_id":[[10042,4],[10016,4]], "consume":[[2,2,100000],[201,432004,45]], "achievement_point":20, "target1":1, "attribute1":[[6,1644]], "target2":"", "attribute2":[]},
	{"id":1001025, "pokedex_level":25, "levelmax":30, "pokedex_id":1001, "hero_id":[[10042,5],[10016,5]], "consume":[[2,2,50000],[201,432004,55]], "achievement_point":0, "target1":1, "attribute1":[[6,1766]], "target2":"", "attribute2":[]},
	{"id":1001026, "pokedex_level":26, "levelmax":30, "pokedex_id":1001, "hero_id":[[10042,5],[10016,5]], "consume":[[2,2,50000],[201,432004,55]], "achievement_point":0, "target1":1, "attribute1":[[6,1889]], "target2":"", "attribute2":[]},
	{"id":1001027, "pokedex_level":27, "levelmax":30, "pokedex_id":1001, "hero_id":[[10042,5],[10016,5]], "consume":[[2,2,50000],[201,432004,65]], "achievement_point":0, "target1":1, "attribute1":[[6,2011]], "target2":"", "attribute2":[]},
	{"id":1001028, "pokedex_level":28, "levelmax":30, "pokedex_id":1001, "hero_id":[[10042,5],[10016,5]], "consume":[[2,2,50000],[201,432004,65]], "achievement_point":0, "target1":1, "attribute1":[[6,2134]], "target2":"", "attribute2":[]},
	{"id":1001029, "pokedex_level":29, "levelmax":30, "pokedex_id":1001, "hero_id":[[10042,5],[10016,5]], "consume":[[2,2,50000],[201,432004,80]], "achievement_point":0, "target1":1, "attribute1":[[6,2256]], "target2":"", "attribute2":[]},
	{"id":1001030, "pokedex_level":30, "levelmax":30, "pokedex_id":1001, "hero_id":[[10042,5],[10016,5]], "consume":[[2,2,200000],[201,432004,80]], "achievement_point":20, "target1":1, "attribute1":[[6,2460]], "target2":"", "attribute2":[]},
	{"id":1002000, "pokedex_level":0, "levelmax":0, "pokedex_id":1002, "hero_id":[[10020,1],[10023,1]], "consume":[], "achievement_point":25, "target1":1, "attribute1":[[4,15]], "target2":"", "attribute2":[]},
	{"id":1002001, "pokedex_level":1, "levelmax":6, "pokedex_id":1002, "hero_id":[[10020,1],[10023,1]], "consume":[[2,2,2500],[201,432004,2]], "achievement_point":0, "target1":1, "attribute1":[[4,24]], "target2":"", "attribute2":[]},
	{"id":1002002, "pokedex_level":2, "levelmax":6, "pokedex_id":1002, "hero_id":[[10020,1],[10023,1]], "consume":[[2,2,2500],[201,432004,2]], "achievement_point":0, "target1":1, "attribute1":[[4,33]], "target2":"", "attribute2":[]},
	{"id":1002003, "pokedex_level":3, "levelmax":6, "pokedex_id":1002, "hero_id":[[10020,1],[10023,1]], "consume":[[2,2,2500],[201,432004,4]], "achievement_point":0, "target1":1, "attribute1":[[4,42]], "target2":"", "attribute2":[]},
	{"id":1002004, "pokedex_level":4, "levelmax":6, "pokedex_id":1002, "hero_id":[[10020,1],[10023,1]], "consume":[[2,2,2500],[201,432004,4]], "achievement_point":0, "target1":1, "attribute1":[[4,51]], "target2":"", "attribute2":[]},
	{"id":1002005, "pokedex_level":5, "levelmax":6, "pokedex_id":1002, "hero_id":[[10020,1],[10023,1]], "consume":[[2,2,2500],[201,432004,6]], "achievement_point":0, "target1":1, "attribute1":[[4,60]], "target2":"", "attribute2":[]},
	{"id":1002006, "pokedex_level":6, "levelmax":6, "pokedex_id":1002, "hero_id":[[10020,1],[10023,1]], "consume":[[2,2,10000],[201,432004,6]], "achievement_point":20, "target1":1, "attribute1":[[4,75]], "target2":"", "attribute2":[]},
	{"id":1002007, "pokedex_level":7, "levelmax":12, "pokedex_id":1002, "hero_id":[[10020,2],[10023,2]], "consume":[[2,2,5000],[201,432004,9]], "achievement_point":0, "target1":1, "attribute1":[[4,87]], "target2":"", "attribute2":[]},
	{"id":1002008, "pokedex_level":8, "levelmax":12, "pokedex_id":1002, "hero_id":[[10020,2],[10023,2]], "consume":[[2,2,5000],[201,432004,9]], "achievement_point":0, "target1":1, "attribute1":[[4,98]], "target2":"", "attribute2":[]},
	{"id":1002009, "pokedex_level":9, "levelmax":12, "pokedex_id":1002, "hero_id":[[10020,2],[10023,2]], "consume":[[2,2,5000],[201,432004,12]], "achievement_point":0, "target1":1, "attribute1":[[4,110]], "target2":"", "attribute2":[]},
	{"id":1002010, "pokedex_level":10, "levelmax":12, "pokedex_id":1002, "hero_id":[[10020,2],[10023,2]], "consume":[[2,2,5000],[201,432004,12]], "achievement_point":0, "target1":1, "attribute1":[[4,122]], "target2":"", "attribute2":[]},
	{"id":1002011, "pokedex_level":11, "levelmax":12, "pokedex_id":1002, "hero_id":[[10020,2],[10023,2]], "consume":[[2,2,5000],[201,432004,15]], "achievement_point":0, "target1":1, "attribute1":[[4,134]], "target2":"", "attribute2":[]},
	{"id":1002012, "pokedex_level":12, "levelmax":12, "pokedex_id":1002, "hero_id":[[10020,2],[10023,2]], "consume":[[2,2,20000],[201,432004,15]], "achievement_point":20, "target1":1, "attribute1":[[4,153]], "target2":"", "attribute2":[]},
	{"id":1002013, "pokedex_level":13, "levelmax":18, "pokedex_id":1002, "hero_id":[[10020,3],[10023,3]], "consume":[[2,2,10000],[201,432004,20]], "achievement_point":0, "target1":1, "attribute1":[[4,169]], "target2":"", "attribute2":[]},
	{"id":1002014, "pokedex_level":14, "levelmax":18, "pokedex_id":1002, "hero_id":[[10020,3],[10023,3]], "consume":[[2,2,10000],[201,432004,20]], "achievement_point":0, "target1":1, "attribute1":[[4,185]], "target2":"", "attribute2":[]},
	{"id":1002015, "pokedex_level":15, "levelmax":18, "pokedex_id":1002, "hero_id":[[10020,3],[10023,3]], "consume":[[2,2,10000],[201,432004,25]], "achievement_point":0, "target1":1, "attribute1":[[4,202]], "target2":"", "attribute2":[]},
	{"id":1002016, "pokedex_level":16, "levelmax":18, "pokedex_id":1002, "hero_id":[[10020,3],[10023,3]], "consume":[[2,2,10000],[201,432004,25]], "achievement_point":0, "target1":1, "attribute1":[[4,218]], "target2":"", "attribute2":[]},
	{"id":1002017, "pokedex_level":17, "levelmax":18, "pokedex_id":1002, "hero_id":[[10020,3],[10023,3]], "consume":[[2,2,10000],[201,432004,30]], "achievement_point":0, "target1":1, "attribute1":[[4,234]], "target2":"", "attribute2":[]},
	{"id":1002018, "pokedex_level":18, "levelmax":18, "pokedex_id":1002, "hero_id":[[10020,3],[10023,3]], "consume":[[2,2,50000],[201,432004,30]], "achievement_point":20, "target1":1, "attribute1":[[4,261]], "target2":"", "attribute2":[]},
	{"id":1002019, "pokedex_level":19, "levelmax":24, "pokedex_id":1002, "hero_id":[[10020,4],[10023,4]], "consume":[[2,2,20000],[201,432004,35]], "achievement_point":0, "target1":1, "attribute1":[[4,284]], "target2":"", "attribute2":[]},
	{"id":1002020, "pokedex_level":20, "levelmax":24, "pokedex_id":1002, "hero_id":[[10020,4],[10023,4]], "consume":[[2,2,20000],[201,432004,35]], "achievement_point":0, "target1":1, "attribute1":[[4,306]], "target2":"", "attribute2":[]},
	{"id":1002021, "pokedex_level":21, "levelmax":24, "pokedex_id":1002, "hero_id":[[10020,4],[10023,4]], "consume":[[2,2,20000],[201,432004,40]], "achievement_point":0, "target1":1, "attribute1":[[4,329]], "target2":"", "attribute2":[]},
	{"id":1002022, "pokedex_level":22, "levelmax":24, "pokedex_id":1002, "hero_id":[[10020,4],[10023,4]], "consume":[[2,2,20000],[201,432004,40]], "achievement_point":0, "target1":1, "attribute1":[[4,351]], "target2":"", "attribute2":[]},
	{"id":1002023, "pokedex_level":23, "levelmax":24, "pokedex_id":1002, "hero_id":[[10020,4],[10023,4]], "consume":[[2,2,20000],[201,432004,45]], "achievement_point":0, "target1":1, "attribute1":[[4,374]], "target2":"", "attribute2":[]},
	{"id":1002024, "pokedex_level":24, "levelmax":24, "pokedex_id":1002, "hero_id":[[10020,4],[10023,4]], "consume":[[2,2,100000],[201,432004,45]], "achievement_point":20, "target1":1, "attribute1":[[4,411]], "target2":"", "attribute2":[]},
	{"id":1002025, "pokedex_level":25, "levelmax":30, "pokedex_id":1002, "hero_id":[[10020,5],[10023,5]], "consume":[[2,2,50000],[201,432004,55]], "achievement_point":0, "target1":1, "attribute1":[[4,442]], "target2":"", "attribute2":[]},
	{"id":1002026, "pokedex_level":26, "levelmax":30, "pokedex_id":1002, "hero_id":[[10020,5],[10023,5]], "consume":[[2,2,50000],[201,432004,55]], "achievement_point":0, "target1":1, "attribute1":[[4,472]], "target2":"", "attribute2":[]},
	{"id":1002027, "pokedex_level":27, "levelmax":30, "pokedex_id":1002, "hero_id":[[10020,5],[10023,5]], "consume":[[2,2,50000],[201,432004,65]], "achievement_point":0, "target1":1, "attribute1":[[4,503]], "target2":"", "attribute2":[]},
	{"id":1002028, "pokedex_level":28, "levelmax":30, "pokedex_id":1002, "hero_id":[[10020,5],[10023,5]], "consume":[[2,2,50000],[201,432004,65]], "achievement_point":0, "target1":1, "attribute1":[[4,533]], "target2":"", "attribute2":[]},
	{"id":1002029, "pokedex_level":29, "levelmax":30, "pokedex_id":1002, "hero_id":[[10020,5],[10023,5]], "consume":[[2,2,50000],[201,432004,80]], "achievement_point":0, "target1":1, "attribute1":[[4,564]], "target2":"", "attribute2":[]},
	{"id":1002030, "pokedex_level":30, "levelmax":30, "pokedex_id":1002, "hero_id":[[10020,5],[10023,5]], "consume":[[2,2,200000],[201,432004,80]], "achievement_point":20, "target1":1, "attribute1":[[4,615]], "target2":"", "attribute2":[]},
	{"id":1003000, "pokedex_level":0, "levelmax":0, "pokedex_id":1003, "hero_id":[[10049,1],[10017,1]], "consume":[], "achievement_point":25, "target1":1, "attribute1":[[5,8]], "target2":"", "attribute2":[]},
	{"id":1003001, "pokedex_level":1, "levelmax":6, "pokedex_id":1003, "hero_id":[[10049,1],[10017,1]], "consume":[[2,2,2500],[201,432004,2]], "achievement_point":0, "target1":1, "attribute1":[[5,12]], "target2":"", "attribute2":[]},
	{"id":1003002, "pokedex_level":2, "levelmax":6, "pokedex_id":1003, "hero_id":[[10049,1],[10017,1]], "consume":[[2,2,2500],[201,432004,2]], "achievement_point":0, "target1":1, "attribute1":[[5,17]], "target2":"", "attribute2":[]},
	{"id":1003003, "pokedex_level":3, "levelmax":6, "pokedex_id":1003, "hero_id":[[10049,1],[10017,1]], "consume":[[2,2,2500],[201,432004,4]], "achievement_point":0, "target1":1, "attribute1":[[5,21]], "target2":"", "attribute2":[]},
	{"id":1003004, "pokedex_level":4, "levelmax":6, "pokedex_id":1003, "hero_id":[[10049,1],[10017,1]], "consume":[[2,2,2500],[201,432004,4]], "achievement_point":0, "target1":1, "attribute1":[[5,26]], "target2":"", "attribute2":[]},
	{"id":1003005, "pokedex_level":5, "levelmax":6, "pokedex_id":1003, "hero_id":[[10049,1],[10017,1]], "consume":[[2,2,2500],[201,432004,6]], "achievement_point":0, "target1":1, "attribute1":[[5,30]], "target2":"", "attribute2":[]},
	{"id":1003006, "pokedex_level":6, "levelmax":6, "pokedex_id":1003, "hero_id":[[10049,1],[10017,1]], "consume":[[2,2,10000],[201,432004,6]], "achievement_point":20, "target1":1, "attribute1":[[5,38]], "target2":"", "attribute2":[]},
	{"id":1003007, "pokedex_level":7, "levelmax":12, "pokedex_id":1003, "hero_id":[[10049,2],[10017,2]], "consume":[[2,2,5000],[201,432004,9]], "achievement_point":0, "target1":1, "attribute1":[[5,43]], "target2":"", "attribute2":[]},
	{"id":1003008, "pokedex_level":8, "levelmax":12, "pokedex_id":1003, "hero_id":[[10049,2],[10017,2]], "consume":[[2,2,5000],[201,432004,9]], "achievement_point":0, "target1":1, "attribute1":[[5,49]], "target2":"", "attribute2":[]},
	{"id":1003009, "pokedex_level":9, "levelmax":12, "pokedex_id":1003, "hero_id":[[10049,2],[10017,2]], "consume":[[2,2,5000],[201,432004,12]], "achievement_point":0, "target1":1, "attribute1":[[5,55]], "target2":"", "attribute2":[]},
	{"id":1003010, "pokedex_level":10, "levelmax":12, "pokedex_id":1003, "hero_id":[[10049,2],[10017,2]], "consume":[[2,2,5000],[201,432004,12]], "achievement_point":0, "target1":1, "attribute1":[[5,61]], "target2":"", "attribute2":[]},
	{"id":1003011, "pokedex_level":11, "levelmax":12, "pokedex_id":1003, "hero_id":[[10049,2],[10017,2]], "consume":[[2,2,5000],[201,432004,15]], "achievement_point":0, "target1":1, "attribute1":[[5,67]], "target2":"", "attribute2":[]},
	{"id":1003012, "pokedex_level":12, "levelmax":12, "pokedex_id":1003, "hero_id":[[10049,2],[10017,2]], "consume":[[2,2,20000],[201,432004,15]], "achievement_point":20, "target1":1, "attribute1":[[5,77]], "target2":"", "attribute2":[]},
	{"id":1003013, "pokedex_level":13, "levelmax":18, "pokedex_id":1003, "hero_id":[[10049,3],[10017,3]], "consume":[[2,2,10000],[201,432004,20]], "achievement_point":0, "target1":1, "attribute1":[[5,85]], "target2":"", "attribute2":[]},
	{"id":1003014, "pokedex_level":14, "levelmax":18, "pokedex_id":1003, "hero_id":[[10049,3],[10017,3]], "consume":[[2,2,10000],[201,432004,20]], "achievement_point":0, "target1":1, "attribute1":[[5,93]], "target2":"", "attribute2":[]},
	{"id":1003015, "pokedex_level":15, "levelmax":18, "pokedex_id":1003, "hero_id":[[10049,3],[10017,3]], "consume":[[2,2,10000],[201,432004,25]], "achievement_point":0, "target1":1, "attribute1":[[5,101]], "target2":"", "attribute2":[]},
	{"id":1003016, "pokedex_level":16, "levelmax":18, "pokedex_id":1003, "hero_id":[[10049,3],[10017,3]], "consume":[[2,2,10000],[201,432004,25]], "achievement_point":0, "target1":1, "attribute1":[[5,109]], "target2":"", "attribute2":[]},
	{"id":1003017, "pokedex_level":17, "levelmax":18, "pokedex_id":1003, "hero_id":[[10049,3],[10017,3]], "consume":[[2,2,10000],[201,432004,30]], "achievement_point":0, "target1":1, "attribute1":[[5,117]], "target2":"", "attribute2":[]},
	{"id":1003018, "pokedex_level":18, "levelmax":18, "pokedex_id":1003, "hero_id":[[10049,3],[10017,3]], "consume":[[2,2,50000],[201,432004,30]], "achievement_point":20, "target1":1, "attribute1":[[5,131]], "target2":"", "attribute2":[]},
	{"id":1003019, "pokedex_level":19, "levelmax":24, "pokedex_id":1003, "hero_id":[[10049,4],[10017,4]], "consume":[[2,2,20000],[201,432004,35]], "achievement_point":0, "target1":1, "attribute1":[[5,142]], "target2":"", "attribute2":[]},
	{"id":1003020, "pokedex_level":20, "levelmax":24, "pokedex_id":1003, "hero_id":[[10049,4],[10017,4]], "consume":[[2,2,20000],[201,432004,35]], "achievement_point":0, "target1":1, "attribute1":[[5,153]], "target2":"", "attribute2":[]},
	{"id":1003021, "pokedex_level":21, "levelmax":24, "pokedex_id":1003, "hero_id":[[10049,4],[10017,4]], "consume":[[2,2,20000],[201,432004,40]], "achievement_point":0, "target1":1, "attribute1":[[5,164]], "target2":"", "attribute2":[]},
	{"id":1003022, "pokedex_level":22, "levelmax":24, "pokedex_id":1003, "hero_id":[[10049,4],[10017,4]], "consume":[[2,2,20000],[201,432004,40]], "achievement_point":0, "target1":1, "attribute1":[[5,176]], "target2":"", "attribute2":[]},
	{"id":1003023, "pokedex_level":23, "levelmax":24, "pokedex_id":1003, "hero_id":[[10049,4],[10017,4]], "consume":[[2,2,20000],[201,432004,45]], "achievement_point":0, "target1":1, "attribute1":[[5,187]], "target2":"", "attribute2":[]},
	{"id":1003024, "pokedex_level":24, "levelmax":24, "pokedex_id":1003, "hero_id":[[10049,4],[10017,4]], "consume":[[2,2,100000],[201,432004,45]], "achievement_point":20, "target1":1, "attribute1":[[5,206]], "target2":"", "attribute2":[]},
	{"id":1003025, "pokedex_level":25, "levelmax":30, "pokedex_id":1003, "hero_id":[[10049,5],[10017,5]], "consume":[[2,2,50000],[201,432004,55]], "achievement_point":0, "target1":1, "attribute1":[[5,221]], "target2":"", "attribute2":[]},
	{"id":1003026, "pokedex_level":26, "levelmax":30, "pokedex_id":1003, "hero_id":[[10049,5],[10017,5]], "consume":[[2,2,50000],[201,432004,55]], "achievement_point":0, "target1":1, "attribute1":[[5,236]], "target2":"", "attribute2":[]},
	{"id":1003027, "pokedex_level":27, "levelmax":30, "pokedex_id":1003, "hero_id":[[10049,5],[10017,5]], "consume":[[2,2,50000],[201,432004,65]], "achievement_point":0, "target1":1, "attribute1":[[5,251]], "target2":"", "attribute2":[]},
	{"id":1003028, "pokedex_level":28, "levelmax":30, "pokedex_id":1003, "hero_id":[[10049,5],[10017,5]], "consume":[[2,2,50000],[201,432004,65]], "achievement_point":0, "target1":1, "attribute1":[[5,267]], "target2":"", "attribute2":[]},
	{"id":1003029, "pokedex_level":29, "levelmax":30, "pokedex_id":1003, "hero_id":[[10049,5],[10017,5]], "consume":[[2,2,50000],[201,432004,80]], "achievement_point":0, "target1":1, "attribute1":[[5,282]], "target2":"", "attribute2":[]},
	{"id":1003030, "pokedex_level":30, "levelmax":30, "pokedex_id":1003, "hero_id":[[10049,5],[10017,5]], "consume":[[2,2,200000],[201,432004,80]], "achievement_point":20, "target1":1, "attribute1":[[5,308]], "target2":"", "attribute2":[]},
	{"id":1004000, "pokedex_level":0, "levelmax":0, "pokedex_id":1004, "hero_id":[[10021,1],[10009,1],[10018,1]], "consume":[], "achievement_point":25, "target1":7, "attribute1":[[4,10],[5,4],[6,38]], "target2":"", "attribute2":[]},
	{"id":1004001, "pokedex_level":1, "levelmax":6, "pokedex_id":1004, "hero_id":[[10021,1],[10009,1],[10018,1]], "consume":[[2,2,2500],[201,432004,2]], "achievement_point":0, "target1":7, "attribute1":[[4,15],[5,6],[6,62]], "target2":"", "attribute2":[]},
	{"id":1004002, "pokedex_level":2, "levelmax":6, "pokedex_id":1004, "hero_id":[[10021,1],[10009,1],[10018,1]], "consume":[[2,2,2500],[201,432004,2]], "achievement_point":0, "target1":7, "attribute1":[[4,21],[5,8],[6,85]], "target2":"", "attribute2":[]},
	{"id":1004003, "pokedex_level":3, "levelmax":6, "pokedex_id":1004, "hero_id":[[10021,1],[10009,1],[10018,1]], "consume":[[2,2,2500],[201,432004,4]], "achievement_point":0, "target1":7, "attribute1":[[4,27],[5,11],[6,108]], "target2":"", "attribute2":[]},
	{"id":1004004, "pokedex_level":4, "levelmax":6, "pokedex_id":1004, "hero_id":[[10021,1],[10009,1],[10018,1]], "consume":[[2,2,2500],[201,432004,4]], "achievement_point":0, "target1":7, "attribute1":[[4,33],[5,13],[6,131]], "target2":"", "attribute2":[]},
	{"id":1004005, "pokedex_level":5, "levelmax":6, "pokedex_id":1004, "hero_id":[[10021,1],[10009,1],[10018,1]], "consume":[[2,2,2500],[201,432004,6]], "achievement_point":0, "target1":7, "attribute1":[[4,38],[5,15],[6,154]], "target2":"", "attribute2":[]},
	{"id":1004006, "pokedex_level":6, "levelmax":6, "pokedex_id":1004, "hero_id":[[10021,1],[10009,1],[10018,1]], "consume":[[2,2,10000],[201,432004,6]], "achievement_point":20, "target1":7, "attribute1":[[4,48],[5,19],[6,192]], "target2":"", "attribute2":[]},
	{"id":1004007, "pokedex_level":7, "levelmax":12, "pokedex_id":1004, "hero_id":[[10021,2],[10009,2],[10018,2]], "consume":[[2,2,5000],[201,432004,9]], "achievement_point":0, "target1":7, "attribute1":[[4,56],[5,22],[6,222]], "target2":"", "attribute2":[]},
	{"id":1004008, "pokedex_level":8, "levelmax":12, "pokedex_id":1004, "hero_id":[[10021,2],[10009,2],[10018,2]], "consume":[[2,2,5000],[201,432004,9]], "achievement_point":0, "target1":7, "attribute1":[[4,63],[5,25],[6,252]], "target2":"", "attribute2":[]},
	{"id":1004009, "pokedex_level":9, "levelmax":12, "pokedex_id":1004, "hero_id":[[10021,2],[10009,2],[10018,2]], "consume":[[2,2,5000],[201,432004,12]], "achievement_point":0, "target1":7, "attribute1":[[4,71],[5,28],[6,282]], "target2":"", "attribute2":[]},
	{"id":1004010, "pokedex_level":10, "levelmax":12, "pokedex_id":1004, "hero_id":[[10021,2],[10009,2],[10018,2]], "consume":[[2,2,5000],[201,432004,12]], "achievement_point":0, "target1":7, "attribute1":[[4,78],[5,31],[6,312]], "target2":"", "attribute2":[]},
	{"id":1004011, "pokedex_level":11, "levelmax":12, "pokedex_id":1004, "hero_id":[[10021,2],[10009,2],[10018,2]], "consume":[[2,2,5000],[201,432004,15]], "achievement_point":0, "target1":7, "attribute1":[[4,86],[5,34],[6,342]], "target2":"", "attribute2":[]},
	{"id":1004012, "pokedex_level":12, "levelmax":12, "pokedex_id":1004, "hero_id":[[10021,2],[10009,2],[10018,2]], "consume":[[2,2,20000],[201,432004,15]], "achievement_point":20, "target1":7, "attribute1":[[4,98],[5,39],[6,392]], "target2":"", "attribute2":[]},
	{"id":1004013, "pokedex_level":13, "levelmax":18, "pokedex_id":1004, "hero_id":[[10021,3],[10009,3],[10018,3]], "consume":[[2,2,10000],[201,432004,20]], "achievement_point":0, "target1":7, "attribute1":[[4,108],[5,43],[6,434]], "target2":"", "attribute2":[]},
	{"id":1004014, "pokedex_level":14, "levelmax":18, "pokedex_id":1004, "hero_id":[[10021,3],[10009,3],[10018,3]], "consume":[[2,2,10000],[201,432004,20]], "achievement_point":0, "target1":7, "attribute1":[[4,119],[5,48],[6,475]], "target2":"", "attribute2":[]},
	{"id":1004015, "pokedex_level":15, "levelmax":18, "pokedex_id":1004, "hero_id":[[10021,3],[10009,3],[10018,3]], "consume":[[2,2,10000],[201,432004,25]], "achievement_point":0, "target1":7, "attribute1":[[4,129],[5,52],[6,517]], "target2":"", "attribute2":[]},
	{"id":1004016, "pokedex_level":16, "levelmax":18, "pokedex_id":1004, "hero_id":[[10021,3],[10009,3],[10018,3]], "consume":[[2,2,10000],[201,432004,25]], "achievement_point":0, "target1":7, "attribute1":[[4,140],[5,56],[6,558]], "target2":"", "attribute2":[]},
	{"id":1004017, "pokedex_level":17, "levelmax":18, "pokedex_id":1004, "hero_id":[[10021,3],[10009,3],[10018,3]], "consume":[[2,2,10000],[201,432004,30]], "achievement_point":0, "target1":7, "attribute1":[[4,150],[5,60],[6,600]], "target2":"", "attribute2":[]},
	{"id":1004018, "pokedex_level":18, "levelmax":18, "pokedex_id":1004, "hero_id":[[10021,3],[10009,3],[10018,3]], "consume":[[2,2,50000],[201,432004,30]], "achievement_point":20, "target1":7, "attribute1":[[4,167],[5,67],[6,669]], "target2":"", "attribute2":[]},
	{"id":1004019, "pokedex_level":19, "levelmax":24, "pokedex_id":1004, "hero_id":[[10021,4],[10009,4],[10018,4]], "consume":[[2,2,20000],[201,432004,35]], "achievement_point":0, "target1":7, "attribute1":[[4,182],[5,73],[6,727]], "target2":"", "attribute2":[]},
	{"id":1004020, "pokedex_level":20, "levelmax":24, "pokedex_id":1004, "hero_id":[[10021,4],[10009,4],[10018,4]], "consume":[[2,2,20000],[201,432004,35]], "achievement_point":0, "target1":7, "attribute1":[[4,196],[5,78],[6,785]], "target2":"", "attribute2":[]},
	{"id":1004021, "pokedex_level":21, "levelmax":24, "pokedex_id":1004, "hero_id":[[10021,4],[10009,4],[10018,4]], "consume":[[2,2,20000],[201,432004,40]], "achievement_point":0, "target1":7, "attribute1":[[4,211],[5,84],[6,842]], "target2":"", "attribute2":[]},
	{"id":1004022, "pokedex_level":22, "levelmax":24, "pokedex_id":1004, "hero_id":[[10021,4],[10009,4],[10018,4]], "consume":[[2,2,20000],[201,432004,40]], "achievement_point":0, "target1":7, "attribute1":[[4,225],[5,90],[6,900]], "target2":"", "attribute2":[]},
	{"id":1004023, "pokedex_level":23, "levelmax":24, "pokedex_id":1004, "hero_id":[[10021,4],[10009,4],[10018,4]], "consume":[[2,2,20000],[201,432004,45]], "achievement_point":0, "target1":7, "attribute1":[[4,239],[5,96],[6,958]], "target2":"", "attribute2":[]},
	{"id":1004024, "pokedex_level":24, "levelmax":24, "pokedex_id":1004, "hero_id":[[10021,4],[10009,4],[10018,4]], "consume":[[2,2,100000],[201,432004,45]], "achievement_point":20, "target1":7, "attribute1":[[4,263],[5,105],[6,1054]], "target2":"", "attribute2":[]},
	{"id":1004025, "pokedex_level":25, "levelmax":30, "pokedex_id":1004, "hero_id":[[10021,5],[10009,5],[10018,4]], "consume":[[2,2,50000],[201,432004,55]], "achievement_point":0, "target1":7, "attribute1":[[4,283],[5,113],[6,1132]], "target2":"", "attribute2":[]},
	{"id":1004026, "pokedex_level":26, "levelmax":30, "pokedex_id":1004, "hero_id":[[10021,5],[10009,5],[10018,4]], "consume":[[2,2,50000],[201,432004,55]], "achievement_point":0, "target1":7, "attribute1":[[4,303],[5,121],[6,1211]], "target2":"", "attribute2":[]},
	{"id":1004027, "pokedex_level":27, "levelmax":30, "pokedex_id":1004, "hero_id":[[10021,5],[10009,5],[10018,4]], "consume":[[2,2,50000],[201,432004,65]], "achievement_point":0, "target1":7, "attribute1":[[4,322],[5,129],[6,1289]], "target2":"", "attribute2":[]},
	{"id":1004028, "pokedex_level":28, "levelmax":30, "pokedex_id":1004, "hero_id":[[10021,5],[10009,5],[10018,4]], "consume":[[2,2,50000],[201,432004,65]], "achievement_point":0, "target1":7, "attribute1":[[4,342],[5,137],[6,1368]], "target2":"", "attribute2":[]},
	{"id":1004029, "pokedex_level":29, "levelmax":30, "pokedex_id":1004, "hero_id":[[10021,5],[10009,5],[10018,4]], "consume":[[2,2,50000],[201,432004,80]], "achievement_point":0, "target1":7, "attribute1":[[4,362],[5,145],[6,1446]], "target2":"", "attribute2":[]},
	{"id":1004030, "pokedex_level":30, "levelmax":30, "pokedex_id":1004, "hero_id":[[10021,5],[10009,5],[10018,4]], "consume":[[2,2,200000],[201,432004,80]], "achievement_point":20, "target1":7, "attribute1":[[4,394],[5,158],[6,1577]], "target2":"", "attribute2":[]},
	{"id":1005000, "pokedex_level":0, "levelmax":0, "pokedex_id":1005, "hero_id":[[10022,1],[10003,1],[10037,1]], "consume":[], "achievement_point":25, "target1":6, "attribute1":[[4,13],[5,3],[6,27]], "target2":"", "attribute2":[]},
	{"id":1005001, "pokedex_level":1, "levelmax":6, "pokedex_id":1005, "hero_id":[[10022,1],[10003,1],[10037,1]], "consume":[[2,2,2500],[201,432004,2]], "achievement_point":0, "target1":6, "attribute1":[[4,22],[5,5],[6,43]], "target2":"", "attribute2":[]},
	{"id":1005002, "pokedex_level":2, "levelmax":6, "pokedex_id":1005, "hero_id":[[10022,1],[10003,1],[10037,1]], "consume":[[2,2,2500],[201,432004,2]], "achievement_point":0, "target1":6, "attribute1":[[4,30],[5,7],[6,59]], "target2":"", "attribute2":[]},
	{"id":1005003, "pokedex_level":3, "levelmax":6, "pokedex_id":1005, "hero_id":[[10022,1],[10003,1],[10037,1]], "consume":[[2,2,2500],[201,432004,4]], "achievement_point":0, "target1":6, "attribute1":[[4,38],[5,9],[6,75]], "target2":"", "attribute2":[]},
	{"id":1005004, "pokedex_level":4, "levelmax":6, "pokedex_id":1005, "hero_id":[[10022,1],[10003,1],[10037,1]], "consume":[[2,2,2500],[201,432004,4]], "achievement_point":0, "target1":6, "attribute1":[[4,46],[5,10],[6,92]], "target2":"", "attribute2":[]},
	{"id":1005005, "pokedex_level":5, "levelmax":6, "pokedex_id":1005, "hero_id":[[10022,1],[10003,1],[10037,1]], "consume":[[2,2,2500],[201,432004,6]], "achievement_point":0, "target1":6, "attribute1":[[4,54],[5,12],[6,108]], "target2":"", "attribute2":[]},
	{"id":1005006, "pokedex_level":6, "levelmax":6, "pokedex_id":1005, "hero_id":[[10022,1],[10003,1],[10037,1]], "consume":[[2,2,10000],[201,432004,6]], "achievement_point":20, "target1":6, "attribute1":[[4,67],[5,15],[6,135]], "target2":"", "attribute2":[]},
	{"id":1005007, "pokedex_level":7, "levelmax":12, "pokedex_id":1005, "hero_id":[[10022,2],[10003,2],[10037,2]], "consume":[[2,2,5000],[201,432004,9]], "achievement_point":0, "target1":6, "attribute1":[[4,78],[5,18],[6,156]], "target2":"", "attribute2":[]},
	{"id":1005008, "pokedex_level":8, "levelmax":12, "pokedex_id":1005, "hero_id":[[10022,2],[10003,2],[10037,2]], "consume":[[2,2,5000],[201,432004,9]], "achievement_point":0, "target1":6, "attribute1":[[4,88],[5,20],[6,177]], "target2":"", "attribute2":[]},
	{"id":1005009, "pokedex_level":9, "levelmax":12, "pokedex_id":1005, "hero_id":[[10022,2],[10003,2],[10037,2]], "consume":[[2,2,5000],[201,432004,12]], "achievement_point":0, "target1":6, "attribute1":[[4,99],[5,23],[6,198]], "target2":"", "attribute2":[]},
	{"id":1005010, "pokedex_level":10, "levelmax":12, "pokedex_id":1005, "hero_id":[[10022,2],[10003,2],[10037,2]], "consume":[[2,2,5000],[201,432004,12]], "achievement_point":0, "target1":6, "attribute1":[[4,109],[5,25],[6,219]], "target2":"", "attribute2":[]},
	{"id":1005011, "pokedex_level":11, "levelmax":12, "pokedex_id":1005, "hero_id":[[10022,2],[10003,2],[10037,2]], "consume":[[2,2,5000],[201,432004,15]], "achievement_point":0, "target1":6, "attribute1":[[4,120],[5,27],[6,240]], "target2":"", "attribute2":[]},
	{"id":1005012, "pokedex_level":12, "levelmax":12, "pokedex_id":1005, "hero_id":[[10022,2],[10003,2],[10037,2]], "consume":[[2,2,20000],[201,432004,15]], "achievement_point":20, "target1":6, "attribute1":[[4,137],[5,31],[6,275]], "target2":"", "attribute2":[]},
	{"id":1005013, "pokedex_level":13, "levelmax":18, "pokedex_id":1005, "hero_id":[[10022,3],[10003,3],[10037,3]], "consume":[[2,2,10000],[201,432004,20]], "achievement_point":0, "target1":6, "attribute1":[[4,152],[5,35],[6,304]], "target2":"", "attribute2":[]},
	{"id":1005014, "pokedex_level":14, "levelmax":18, "pokedex_id":1005, "hero_id":[[10022,3],[10003,3],[10037,3]], "consume":[[2,2,10000],[201,432004,20]], "achievement_point":0, "target1":6, "attribute1":[[4,166],[5,38],[6,333]], "target2":"", "attribute2":[]},
	{"id":1005015, "pokedex_level":15, "levelmax":18, "pokedex_id":1005, "hero_id":[[10022,3],[10003,3],[10037,3]], "consume":[[2,2,10000],[201,432004,25]], "achievement_point":0, "target1":6, "attribute1":[[4,181],[5,41],[6,362]], "target2":"", "attribute2":[]},
	{"id":1005016, "pokedex_level":16, "levelmax":18, "pokedex_id":1005, "hero_id":[[10022,3],[10003,3],[10037,3]], "consume":[[2,2,10000],[201,432004,25]], "achievement_point":0, "target1":6, "attribute1":[[4,195],[5,45],[6,391]], "target2":"", "attribute2":[]},
	{"id":1005017, "pokedex_level":17, "levelmax":18, "pokedex_id":1005, "hero_id":[[10022,3],[10003,3],[10037,3]], "consume":[[2,2,10000],[201,432004,30]], "achievement_point":0, "target1":6, "attribute1":[[4,210],[5,48],[6,420]], "target2":"", "attribute2":[]},
	{"id":1005018, "pokedex_level":18, "levelmax":18, "pokedex_id":1005, "hero_id":[[10022,3],[10003,3],[10037,3]], "consume":[[2,2,50000],[201,432004,30]], "achievement_point":20, "target1":6, "attribute1":[[4,234],[5,54],[6,468]], "target2":"", "attribute2":[]},
	{"id":1005019, "pokedex_level":19, "levelmax":24, "pokedex_id":1005, "hero_id":[[10022,4],[10003,4],[10037,4]], "consume":[[2,2,20000],[201,432004,35]], "achievement_point":0, "target1":6, "attribute1":[[4,254],[5,58],[6,509]], "target2":"", "attribute2":[]},
	{"id":1005020, "pokedex_level":20, "levelmax":24, "pokedex_id":1005, "hero_id":[[10022,4],[10003,4],[10037,4]], "consume":[[2,2,20000],[201,432004,35]], "achievement_point":0, "target1":6, "attribute1":[[4,275],[5,63],[6,549]], "target2":"", "attribute2":[]},
	{"id":1005021, "pokedex_level":21, "levelmax":24, "pokedex_id":1005, "hero_id":[[10022,4],[10003,4],[10037,4]], "consume":[[2,2,20000],[201,432004,40]], "achievement_point":0, "target1":6, "attribute1":[[4,295],[5,67],[6,590]], "target2":"", "attribute2":[]},
	{"id":1005022, "pokedex_level":22, "levelmax":24, "pokedex_id":1005, "hero_id":[[10022,4],[10003,4],[10037,4]], "consume":[[2,2,20000],[201,432004,40]], "achievement_point":0, "target1":6, "attribute1":[[4,315],[5,72],[6,630]], "target2":"", "attribute2":[]},
	{"id":1005023, "pokedex_level":23, "levelmax":24, "pokedex_id":1005, "hero_id":[[10022,4],[10003,4],[10037,4]], "consume":[[2,2,20000],[201,432004,45]], "achievement_point":0, "target1":6, "attribute1":[[4,335],[5,77],[6,670]], "target2":"", "attribute2":[]},
	{"id":1005024, "pokedex_level":24, "levelmax":24, "pokedex_id":1005, "hero_id":[[10022,4],[10003,4],[10037,4]], "consume":[[2,2,100000],[201,432004,45]], "achievement_point":20, "target1":6, "attribute1":[[4,369],[5,84],[6,738]], "target2":"", "attribute2":[]},
	{"id":1005025, "pokedex_level":25, "levelmax":30, "pokedex_id":1005, "hero_id":[[10022,5],[10003,5],[10037,4]], "consume":[[2,2,50000],[201,432004,55]], "achievement_point":0, "target1":6, "attribute1":[[4,396],[5,91],[6,793]], "target2":"", "attribute2":[]},
	{"id":1005026, "pokedex_level":26, "levelmax":30, "pokedex_id":1005, "hero_id":[[10022,5],[10003,5],[10037,4]], "consume":[[2,2,50000],[201,432004,55]], "achievement_point":0, "target1":6, "attribute1":[[4,424],[5,97],[6,848]], "target2":"", "attribute2":[]},
	{"id":1005027, "pokedex_level":27, "levelmax":30, "pokedex_id":1005, "hero_id":[[10022,5],[10003,5],[10037,4]], "consume":[[2,2,50000],[201,432004,65]], "achievement_point":0, "target1":6, "attribute1":[[4,451],[5,103],[6,902]], "target2":"", "attribute2":[]},
	{"id":1005028, "pokedex_level":28, "levelmax":30, "pokedex_id":1005, "hero_id":[[10022,5],[10003,5],[10037,4]], "consume":[[2,2,50000],[201,432004,65]], "achievement_point":0, "target1":6, "attribute1":[[4,479],[5,109],[6,957]], "target2":"", "attribute2":[]},
	{"id":1005029, "pokedex_level":29, "levelmax":30, "pokedex_id":1005, "hero_id":[[10022,5],[10003,5],[10037,4]], "consume":[[2,2,50000],[201,432004,80]], "achievement_point":0, "target1":6, "attribute1":[[4,506],[5,116],[6,1012]], "target2":"", "attribute2":[]},
	{"id":1005030, "pokedex_level":30, "levelmax":30, "pokedex_id":1005, "hero_id":[[10022,5],[10003,5],[10037,4]], "consume":[[2,2,200000],[201,432004,80]], "achievement_point":20, "target1":6, "attribute1":[[4,552],[5,126],[6,1104]], "target2":"", "attribute2":[]},
	{"id":1006000, "pokedex_level":0, "levelmax":0, "pokedex_id":1006, "hero_id":[[10044,1],[10045,1],[10006,1]], "consume":[], "achievement_point":25, "target1":5, "attribute1":[[4,7],[5,5],[6,48]], "target2":"", "attribute2":[]},
	{"id":1006001, "pokedex_level":1, "levelmax":6, "pokedex_id":1006, "hero_id":[[10044,1],[10045,1],[10006,1]], "consume":[[2,2,2500],[201,432004,2]], "achievement_point":0, "target1":5, "attribute1":[[4,11],[5,8],[6,77]], "target2":"", "attribute2":[]},
	{"id":1006002, "pokedex_level":2, "levelmax":6, "pokedex_id":1006, "hero_id":[[10044,1],[10045,1],[10006,1]], "consume":[[2,2,2500],[201,432004,2]], "achievement_point":0, "target1":5, "attribute1":[[4,15],[5,11],[6,106]], "target2":"", "attribute2":[]},
	{"id":1006003, "pokedex_level":3, "levelmax":6, "pokedex_id":1006, "hero_id":[[10044,1],[10045,1],[10006,1]], "consume":[[2,2,2500],[201,432004,4]], "achievement_point":0, "target1":5, "attribute1":[[4,19],[5,13],[6,135]], "target2":"", "attribute2":[]},
	{"id":1006004, "pokedex_level":4, "levelmax":6, "pokedex_id":1006, "hero_id":[[10044,1],[10045,1],[10006,1]], "consume":[[2,2,2500],[201,432004,4]], "achievement_point":0, "target1":5, "attribute1":[[4,23],[5,16],[6,163]], "target2":"", "attribute2":[]},
	{"id":1006005, "pokedex_level":5, "levelmax":6, "pokedex_id":1006, "hero_id":[[10044,1],[10045,1],[10006,1]], "consume":[[2,2,2500],[201,432004,6]], "achievement_point":0, "target1":5, "attribute1":[[4,27],[5,19],[6,192]], "target2":"", "attribute2":[]},
	{"id":1006006, "pokedex_level":6, "levelmax":6, "pokedex_id":1006, "hero_id":[[10044,1],[10045,1],[10006,1]], "consume":[[2,2,10000],[201,432004,6]], "achievement_point":20, "target1":5, "attribute1":[[4,34],[5,24],[6,240]], "target2":"", "attribute2":[]},
	{"id":1006007, "pokedex_level":7, "levelmax":12, "pokedex_id":1006, "hero_id":[[10044,2],[10045,2],[10006,2]], "consume":[[2,2,5000],[201,432004,9]], "achievement_point":0, "target1":5, "attribute1":[[4,39],[5,28],[6,278]], "target2":"", "attribute2":[]},
	{"id":1006008, "pokedex_level":8, "levelmax":12, "pokedex_id":1006, "hero_id":[[10044,2],[10045,2],[10006,2]], "consume":[[2,2,5000],[201,432004,9]], "achievement_point":0, "target1":5, "attribute1":[[4,44],[5,32],[6,315]], "target2":"", "attribute2":[]},
	{"id":1006009, "pokedex_level":9, "levelmax":12, "pokedex_id":1006, "hero_id":[[10044,2],[10045,2],[10006,2]], "consume":[[2,2,5000],[201,432004,12]], "achievement_point":0, "target1":5, "attribute1":[[4,49],[5,35],[6,353]], "target2":"", "attribute2":[]},
	{"id":1006010, "pokedex_level":10, "levelmax":12, "pokedex_id":1006, "hero_id":[[10044,2],[10045,2],[10006,2]], "consume":[[2,2,5000],[201,432004,12]], "achievement_point":0, "target1":5, "attribute1":[[4,55],[5,39],[6,390]], "target2":"", "attribute2":[]},
	{"id":1006011, "pokedex_level":11, "levelmax":12, "pokedex_id":1006, "hero_id":[[10044,2],[10045,2],[10006,2]], "consume":[[2,2,5000],[201,432004,15]], "achievement_point":0, "target1":5, "attribute1":[[4,60],[5,43],[6,428]], "target2":"", "attribute2":[]},
	{"id":1006012, "pokedex_level":12, "levelmax":12, "pokedex_id":1006, "hero_id":[[10044,2],[10045,2],[10006,2]], "consume":[[2,2,20000],[201,432004,15]], "achievement_point":20, "target1":5, "attribute1":[[4,69],[5,49],[6,490]], "target2":"", "attribute2":[]},
	{"id":1006013, "pokedex_level":13, "levelmax":18, "pokedex_id":1006, "hero_id":[[10044,3],[10045,3],[10006,3]], "consume":[[2,2,10000],[201,432004,20]], "achievement_point":0, "target1":5, "attribute1":[[4,76],[5,54],[6,542]], "target2":"", "attribute2":[]},
	{"id":1006014, "pokedex_level":14, "levelmax":18, "pokedex_id":1006, "hero_id":[[10044,3],[10045,3],[10006,3]], "consume":[[2,2,10000],[201,432004,20]], "achievement_point":0, "target1":5, "attribute1":[[4,83],[5,59],[6,594]], "target2":"", "attribute2":[]},
	{"id":1006015, "pokedex_level":15, "levelmax":18, "pokedex_id":1006, "hero_id":[[10044,3],[10045,3],[10006,3]], "consume":[[2,2,10000],[201,432004,25]], "achievement_point":0, "target1":5, "attribute1":[[4,90],[5,65],[6,646]], "target2":"", "attribute2":[]},
	{"id":1006016, "pokedex_level":16, "levelmax":18, "pokedex_id":1006, "hero_id":[[10044,3],[10045,3],[10006,3]], "consume":[[2,2,10000],[201,432004,25]], "achievement_point":0, "target1":5, "attribute1":[[4,98],[5,70],[6,698]], "target2":"", "attribute2":[]},
	{"id":1006017, "pokedex_level":17, "levelmax":18, "pokedex_id":1006, "hero_id":[[10044,3],[10045,3],[10006,3]], "consume":[[2,2,10000],[201,432004,30]], "achievement_point":0, "target1":5, "attribute1":[[4,105],[5,75],[6,750]], "target2":"", "attribute2":[]},
	{"id":1006018, "pokedex_level":18, "levelmax":18, "pokedex_id":1006, "hero_id":[[10044,3],[10045,3],[10006,3]], "consume":[[2,2,50000],[201,432004,30]], "achievement_point":20, "target1":5, "attribute1":[[4,117],[5,84],[6,837]], "target2":"", "attribute2":[]},
	{"id":1006019, "pokedex_level":19, "levelmax":24, "pokedex_id":1006, "hero_id":[[10044,4],[10045,4],[10006,4]], "consume":[[2,2,20000],[201,432004,35]], "achievement_point":0, "target1":5, "attribute1":[[4,127],[5,91],[6,909]], "target2":"", "attribute2":[]},
	{"id":1006020, "pokedex_level":20, "levelmax":24, "pokedex_id":1006, "hero_id":[[10044,4],[10045,4],[10006,4]], "consume":[[2,2,20000],[201,432004,35]], "achievement_point":0, "target1":5, "attribute1":[[4,137],[5,98],[6,981]], "target2":"", "attribute2":[]},
	{"id":1006021, "pokedex_level":21, "levelmax":24, "pokedex_id":1006, "hero_id":[[10044,4],[10045,4],[10006,4]], "consume":[[2,2,20000],[201,432004,40]], "achievement_point":0, "target1":5, "attribute1":[[4,147],[5,105],[6,1053]], "target2":"", "attribute2":[]},
	{"id":1006022, "pokedex_level":22, "levelmax":24, "pokedex_id":1006, "hero_id":[[10044,4],[10045,4],[10006,4]], "consume":[[2,2,20000],[201,432004,40]], "achievement_point":0, "target1":5, "attribute1":[[4,158],[5,113],[6,1125]], "target2":"", "attribute2":[]},
	{"id":1006023, "pokedex_level":23, "levelmax":24, "pokedex_id":1006, "hero_id":[[10044,4],[10045,4],[10006,4]], "consume":[[2,2,20000],[201,432004,45]], "achievement_point":0, "target1":5, "attribute1":[[4,168],[5,120],[6,1197]], "target2":"", "attribute2":[]},
	{"id":1006024, "pokedex_level":24, "levelmax":24, "pokedex_id":1006, "hero_id":[[10044,4],[10045,4],[10006,4]], "consume":[[2,2,100000],[201,432004,45]], "achievement_point":20, "target1":5, "attribute1":[[4,184],[5,132],[6,1317]], "target2":"", "attribute2":[]},
	{"id":1006025, "pokedex_level":25, "levelmax":30, "pokedex_id":1006, "hero_id":[[10044,5],[10045,5],[10006,4]], "consume":[[2,2,50000],[201,432004,55]], "achievement_point":0, "target1":5, "attribute1":[[4,198],[5,142],[6,1415]], "target2":"", "attribute2":[]},
	{"id":1006026, "pokedex_level":26, "levelmax":30, "pokedex_id":1006, "hero_id":[[10044,5],[10045,5],[10006,4]], "consume":[[2,2,50000],[201,432004,55]], "achievement_point":0, "target1":5, "attribute1":[[4,212],[5,151],[6,1513]], "target2":"", "attribute2":[]},
	{"id":1006027, "pokedex_level":27, "levelmax":30, "pokedex_id":1006, "hero_id":[[10044,5],[10045,5],[10006,4]], "consume":[[2,2,50000],[201,432004,65]], "achievement_point":0, "target1":5, "attribute1":[[4,226],[5,161],[6,1612]], "target2":"", "attribute2":[]},
	{"id":1006028, "pokedex_level":28, "levelmax":30, "pokedex_id":1006, "hero_id":[[10044,5],[10045,5],[10006,4]], "consume":[[2,2,50000],[201,432004,65]], "achievement_point":0, "target1":5, "attribute1":[[4,239],[5,171],[6,1710]], "target2":"", "attribute2":[]},
	{"id":1006029, "pokedex_level":29, "levelmax":30, "pokedex_id":1006, "hero_id":[[10044,5],[10045,5],[10006,4]], "consume":[[2,2,50000],[201,432004,80]], "achievement_point":0, "target1":5, "attribute1":[[4,253],[5,181],[6,1808]], "target2":"", "attribute2":[]},
	{"id":1006030, "pokedex_level":30, "levelmax":30, "pokedex_id":1006, "hero_id":[[10044,5],[10045,5],[10006,4]], "consume":[[2,2,200000],[201,432004,80]], "achievement_point":20, "target1":5, "attribute1":[[4,276],[5,197],[6,1971]], "target2":"", "attribute2":[]},
	{"id":1007000, "pokedex_level":0, "levelmax":0, "pokedex_id":1007, "hero_id":[[10017,1],[10036,1],[10049,1],[10019,1]], "consume":[], "achievement_point":30, "target1":1, "attribute1":[[4,7],[5,3],[6,28]], "target2":"", "attribute2":[]},
	{"id":1007001, "pokedex_level":1, "levelmax":6, "pokedex_id":1007, "hero_id":[[10017,1],[10036,1],[10049,1],[10019,1]], "consume":[[2,2,2500],[201,432004,2]], "achievement_point":0, "target1":1, "attribute1":[[4,11],[5,4],[6,45]], "target2":"", "attribute2":[]},
	{"id":1007002, "pokedex_level":2, "levelmax":6, "pokedex_id":1007, "hero_id":[[10017,1],[10036,1],[10049,1],[10019,1]], "consume":[[2,2,2500],[201,432004,2]], "achievement_point":0, "target1":1, "attribute1":[[4,15],[5,6],[6,62]], "target2":"", "attribute2":[]},
	{"id":1007003, "pokedex_level":3, "levelmax":6, "pokedex_id":1007, "hero_id":[[10017,1],[10036,1],[10049,1],[10019,1]], "consume":[[2,2,2500],[201,432004,4]], "achievement_point":0, "target1":1, "attribute1":[[4,20],[5,8],[6,78]], "target2":"", "attribute2":[]},
	{"id":1007004, "pokedex_level":4, "levelmax":6, "pokedex_id":1007, "hero_id":[[10017,1],[10036,1],[10049,1],[10019,1]], "consume":[[2,2,2500],[201,432004,4]], "achievement_point":0, "target1":1, "attribute1":[[4,24],[5,10],[6,95]], "target2":"", "attribute2":[]},
	{"id":1007005, "pokedex_level":5, "levelmax":6, "pokedex_id":1007, "hero_id":[[10017,1],[10036,1],[10049,1],[10019,1]], "consume":[[2,2,2500],[201,432004,6]], "achievement_point":0, "target1":1, "attribute1":[[4,28],[5,11],[6,112]], "target2":"", "attribute2":[]},
	{"id":1007006, "pokedex_level":6, "levelmax":6, "pokedex_id":1007, "hero_id":[[10017,1],[10036,1],[10049,1],[10019,1]], "consume":[[2,2,10000],[201,432004,6]], "achievement_point":24, "target1":1, "attribute1":[[4,35],[5,14],[6,140]], "target2":"", "attribute2":[]},
	{"id":1007007, "pokedex_level":7, "levelmax":12, "pokedex_id":1007, "hero_id":[[10017,2],[10036,2],[10049,2],[10019,2]], "consume":[[2,2,5000],[201,432004,9]], "achievement_point":0, "target1":1, "attribute1":[[4,40],[5,16],[6,162]], "target2":"", "attribute2":[]},
	{"id":1007008, "pokedex_level":8, "levelmax":12, "pokedex_id":1007, "hero_id":[[10017,2],[10036,2],[10049,2],[10019,2]], "consume":[[2,2,5000],[201,432004,9]], "achievement_point":0, "target1":1, "attribute1":[[4,46],[5,18],[6,184]], "target2":"", "attribute2":[]},
	{"id":1007009, "pokedex_level":9, "levelmax":12, "pokedex_id":1007, "hero_id":[[10017,2],[10036,2],[10049,2],[10019,2]], "consume":[[2,2,5000],[201,432004,12]], "achievement_point":0, "target1":1, "attribute1":[[4,51],[5,21],[6,206]], "target2":"", "attribute2":[]},
	{"id":1007010, "pokedex_level":10, "levelmax":12, "pokedex_id":1007, "hero_id":[[10017,2],[10036,2],[10049,2],[10019,2]], "consume":[[2,2,5000],[201,432004,12]], "achievement_point":0, "target1":1, "attribute1":[[4,57],[5,23],[6,227]], "target2":"", "attribute2":[]},
	{"id":1007011, "pokedex_level":11, "levelmax":12, "pokedex_id":1007, "hero_id":[[10017,2],[10036,2],[10049,2],[10019,2]], "consume":[[2,2,5000],[201,432004,15]], "achievement_point":0, "target1":1, "attribute1":[[4,62],[5,25],[6,249]], "target2":"", "attribute2":[]},
	{"id":1007012, "pokedex_level":12, "levelmax":12, "pokedex_id":1007, "hero_id":[[10017,2],[10036,2],[10049,2],[10019,2]], "consume":[[2,2,20000],[201,432004,15]], "achievement_point":24, "target1":1, "attribute1":[[4,71],[5,29],[6,286]], "target2":"", "attribute2":[]},
	{"id":1007013, "pokedex_level":13, "levelmax":18, "pokedex_id":1007, "hero_id":[[10017,3],[10036,3],[10049,3],[10019,3]], "consume":[[2,2,10000],[201,432004,20]], "achievement_point":0, "target1":1, "attribute1":[[4,79],[5,32],[6,316]], "target2":"", "attribute2":[]},
	{"id":1007014, "pokedex_level":14, "levelmax":18, "pokedex_id":1007, "hero_id":[[10017,3],[10036,3],[10049,3],[10019,3]], "consume":[[2,2,10000],[201,432004,20]], "achievement_point":0, "target1":1, "attribute1":[[4,87],[5,35],[6,346]], "target2":"", "attribute2":[]},
	{"id":1007015, "pokedex_level":15, "levelmax":18, "pokedex_id":1007, "hero_id":[[10017,3],[10036,3],[10049,3],[10019,3]], "consume":[[2,2,10000],[201,432004,25]], "achievement_point":0, "target1":1, "attribute1":[[4,94],[5,38],[6,376]], "target2":"", "attribute2":[]},
	{"id":1007016, "pokedex_level":16, "levelmax":18, "pokedex_id":1007, "hero_id":[[10017,3],[10036,3],[10049,3],[10019,3]], "consume":[[2,2,10000],[201,432004,25]], "achievement_point":0, "target1":1, "attribute1":[[4,102],[5,41],[6,407]], "target2":"", "attribute2":[]},
	{"id":1007017, "pokedex_level":17, "levelmax":18, "pokedex_id":1007, "hero_id":[[10017,3],[10036,3],[10049,3],[10019,3]], "consume":[[2,2,10000],[201,432004,30]], "achievement_point":0, "target1":1, "attribute1":[[4,109],[5,44],[6,437]], "target2":"", "attribute2":[]},
	{"id":1007018, "pokedex_level":18, "levelmax":18, "pokedex_id":1007, "hero_id":[[10017,3],[10036,3],[10049,3],[10019,3]], "consume":[[2,2,50000],[201,432004,30]], "achievement_point":24, "target1":1, "attribute1":[[4,122],[5,49],[6,487]], "target2":"", "attribute2":[]},
	{"id":1007019, "pokedex_level":19, "levelmax":24, "pokedex_id":1007, "hero_id":[[10017,4],[10036,4],[10049,4],[10019,4]], "consume":[[2,2,20000],[201,432004,35]], "achievement_point":0, "target1":1, "attribute1":[[4,132],[5,53],[6,529]], "target2":"", "attribute2":[]},
	{"id":1007020, "pokedex_level":20, "levelmax":24, "pokedex_id":1007, "hero_id":[[10017,4],[10036,4],[10049,4],[10019,4]], "consume":[[2,2,20000],[201,432004,35]], "achievement_point":0, "target1":1, "attribute1":[[4,143],[5,57],[6,571]], "target2":"", "attribute2":[]},
	{"id":1007021, "pokedex_level":21, "levelmax":24, "pokedex_id":1007, "hero_id":[[10017,4],[10036,4],[10049,4],[10019,4]], "consume":[[2,2,20000],[201,432004,40]], "achievement_point":0, "target1":1, "attribute1":[[4,153],[5,61],[6,613]], "target2":"", "attribute2":[]},
	{"id":1007022, "pokedex_level":22, "levelmax":24, "pokedex_id":1007, "hero_id":[[10017,4],[10036,4],[10049,4],[10019,4]], "consume":[[2,2,20000],[201,432004,40]], "achievement_point":0, "target1":1, "attribute1":[[4,164],[5,66],[6,655]], "target2":"", "attribute2":[]},
	{"id":1007023, "pokedex_level":23, "levelmax":24, "pokedex_id":1007, "hero_id":[[10017,4],[10036,4],[10049,4],[10019,4]], "consume":[[2,2,20000],[201,432004,45]], "achievement_point":0, "target1":1, "attribute1":[[4,174],[5,70],[6,697]], "target2":"", "attribute2":[]},
	{"id":1007024, "pokedex_level":24, "levelmax":24, "pokedex_id":1007, "hero_id":[[10017,4],[10036,4],[10049,4],[10019,4]], "consume":[[2,2,100000],[201,432004,45]], "achievement_point":24, "target1":1, "attribute1":[[4,192],[5,77],[6,767]], "target2":"", "attribute2":[]},
	{"id":1007025, "pokedex_level":25, "levelmax":30, "pokedex_id":1007, "hero_id":[[10017,5],[10036,5],[10049,5],[10019,5]], "consume":[[2,2,50000],[201,432004,55]], "achievement_point":0, "target1":1, "attribute1":[[4,206],[5,82],[6,824]], "target2":"", "attribute2":[]},
	{"id":1007026, "pokedex_level":26, "levelmax":30, "pokedex_id":1007, "hero_id":[[10017,5],[10036,5],[10049,5],[10019,5]], "consume":[[2,2,50000],[201,432004,55]], "achievement_point":0, "target1":1, "attribute1":[[4,220],[5,88],[6,881]], "target2":"", "attribute2":[]},
	{"id":1007027, "pokedex_level":27, "levelmax":30, "pokedex_id":1007, "hero_id":[[10017,5],[10036,5],[10049,5],[10019,5]], "consume":[[2,2,50000],[201,432004,65]], "achievement_point":0, "target1":1, "attribute1":[[4,235],[5,94],[6,939]], "target2":"", "attribute2":[]},
	{"id":1007028, "pokedex_level":28, "levelmax":30, "pokedex_id":1007, "hero_id":[[10017,5],[10036,5],[10049,5],[10019,5]], "consume":[[2,2,50000],[201,432004,65]], "achievement_point":0, "target1":1, "attribute1":[[4,249],[5,100],[6,996]], "target2":"", "attribute2":[]},
	{"id":1007029, "pokedex_level":29, "levelmax":30, "pokedex_id":1007, "hero_id":[[10017,5],[10036,5],[10049,5],[10019,5]], "consume":[[2,2,50000],[201,432004,80]], "achievement_point":0, "target1":1, "attribute1":[[4,263],[5,105],[6,1053]], "target2":"", "attribute2":[]},
	{"id":1007030, "pokedex_level":30, "levelmax":30, "pokedex_id":1007, "hero_id":[[10017,5],[10036,5],[10049,5],[10019,5]], "consume":[[2,2,200000],[201,432004,80]], "achievement_point":24, "target1":1, "attribute1":[[4,287],[5,115],[6,1148]], "target2":"", "attribute2":[]},
	{"id":1008000, "pokedex_level":0, "levelmax":0, "pokedex_id":1008, "hero_id":[[10007,1],[10023,1],[10049,1],[10042,1]], "consume":[], "achievement_point":35, "target1":1, "attribute1":[[4,9],[5,4],[6,36]], "target2":"", "attribute2":[]},
	{"id":1008001, "pokedex_level":1, "levelmax":6, "pokedex_id":1008, "hero_id":[[10007,1],[10023,1],[10049,1],[10042,1]], "consume":[[2,2,2500],[201,432004,3]], "achievement_point":0, "target1":1, "attribute1":[[4,14],[5,6],[6,58]], "target2":"", "attribute2":[]},
	{"id":1008002, "pokedex_level":2, "levelmax":6, "pokedex_id":1008, "hero_id":[[10007,1],[10023,1],[10049,1],[10042,1]], "consume":[[2,2,2500],[201,432004,3]], "achievement_point":0, "target1":1, "attribute1":[[4,20],[5,8],[6,79]], "target2":"", "attribute2":[]},
	{"id":1008003, "pokedex_level":3, "levelmax":6, "pokedex_id":1008, "hero_id":[[10007,1],[10023,1],[10049,1],[10042,1]], "consume":[[2,2,2500],[201,432004,5]], "achievement_point":0, "target1":1, "attribute1":[[4,25],[5,10],[6,101]], "target2":"", "attribute2":[]},
	{"id":1008004, "pokedex_level":4, "levelmax":6, "pokedex_id":1008, "hero_id":[[10007,1],[10023,1],[10049,1],[10042,1]], "consume":[[2,2,2500],[201,432004,5]], "achievement_point":0, "target1":1, "attribute1":[[4,31],[5,12],[6,122]], "target2":"", "attribute2":[]},
	{"id":1008005, "pokedex_level":5, "levelmax":6, "pokedex_id":1008, "hero_id":[[10007,1],[10023,1],[10049,1],[10042,1]], "consume":[[2,2,2500],[201,432004,8]], "achievement_point":0, "target1":1, "attribute1":[[4,36],[5,14],[6,144]], "target2":"", "attribute2":[]},
	{"id":1008006, "pokedex_level":6, "levelmax":6, "pokedex_id":1008, "hero_id":[[10007,1],[10023,1],[10049,1],[10042,1]], "consume":[[2,2,10000],[201,432004,8]], "achievement_point":28, "target1":1, "attribute1":[[4,45],[5,18],[6,180]], "target2":"", "attribute2":[]},
	{"id":1008007, "pokedex_level":7, "levelmax":12, "pokedex_id":1008, "hero_id":[[10007,2],[10023,2],[10049,2],[10042,2]], "consume":[[2,2,5000],[201,432004,12]], "achievement_point":0, "target1":1, "attribute1":[[4,52],[5,21],[6,208]], "target2":"", "attribute2":[]},
	{"id":1008008, "pokedex_level":8, "levelmax":12, "pokedex_id":1008, "hero_id":[[10007,2],[10023,2],[10049,2],[10042,2]], "consume":[[2,2,5000],[201,432004,12]], "achievement_point":0, "target1":1, "attribute1":[[4,59],[5,24],[6,236]], "target2":"", "attribute2":[]},
	{"id":1008009, "pokedex_level":9, "levelmax":12, "pokedex_id":1008, "hero_id":[[10007,2],[10023,2],[10049,2],[10042,2]], "consume":[[2,2,5000],[201,432004,16]], "achievement_point":0, "target1":1, "attribute1":[[4,66],[5,26],[6,264]], "target2":"", "attribute2":[]},
	{"id":1008010, "pokedex_level":10, "levelmax":12, "pokedex_id":1008, "hero_id":[[10007,2],[10023,2],[10049,2],[10042,2]], "consume":[[2,2,5000],[201,432004,16]], "achievement_point":0, "target1":1, "attribute1":[[4,73],[5,29],[6,292]], "target2":"", "attribute2":[]},
	{"id":1008011, "pokedex_level":11, "levelmax":12, "pokedex_id":1008, "hero_id":[[10007,2],[10023,2],[10049,2],[10042,2]], "consume":[[2,2,5000],[201,432004,20]], "achievement_point":0, "target1":1, "attribute1":[[4,80],[5,32],[6,320]], "target2":"", "attribute2":[]},
	{"id":1008012, "pokedex_level":12, "levelmax":12, "pokedex_id":1008, "hero_id":[[10007,2],[10023,2],[10049,2],[10042,2]], "consume":[[2,2,20000],[201,432004,20]], "achievement_point":28, "target1":1, "attribute1":[[4,92],[5,37],[6,367]], "target2":"", "attribute2":[]},
	{"id":1008013, "pokedex_level":13, "levelmax":18, "pokedex_id":1008, "hero_id":[[10007,3],[10023,3],[10049,3],[10042,3]], "consume":[[2,2,10000],[201,432004,24]], "achievement_point":0, "target1":1, "attribute1":[[4,102],[5,41],[6,406]], "target2":"", "attribute2":[]},
	{"id":1008014, "pokedex_level":14, "levelmax":18, "pokedex_id":1008, "hero_id":[[10007,3],[10023,3],[10049,3],[10042,3]], "consume":[[2,2,10000],[201,432004,24]], "achievement_point":0, "target1":1, "attribute1":[[4,111],[5,44],[6,445]], "target2":"", "attribute2":[]},
	{"id":1008015, "pokedex_level":15, "levelmax":18, "pokedex_id":1008, "hero_id":[[10007,3],[10023,3],[10049,3],[10042,3]], "consume":[[2,2,10000],[201,432004,30]], "achievement_point":0, "target1":1, "attribute1":[[4,121],[5,48],[6,484]], "target2":"", "attribute2":[]},
	{"id":1008016, "pokedex_level":16, "levelmax":18, "pokedex_id":1008, "hero_id":[[10007,3],[10023,3],[10049,3],[10042,3]], "consume":[[2,2,10000],[201,432004,30]], "achievement_point":0, "target1":1, "attribute1":[[4,131],[5,52],[6,523]], "target2":"", "attribute2":[]},
	{"id":1008017, "pokedex_level":17, "levelmax":18, "pokedex_id":1008, "hero_id":[[10007,3],[10023,3],[10049,3],[10042,3]], "consume":[[2,2,10000],[201,432004,38]], "achievement_point":0, "target1":1, "attribute1":[[4,140],[5,56],[6,562]], "target2":"", "attribute2":[]},
	{"id":1008018, "pokedex_level":18, "levelmax":18, "pokedex_id":1008, "hero_id":[[10007,3],[10023,3],[10049,3],[10042,3]], "consume":[[2,2,50000],[201,432004,38]], "achievement_point":28, "target1":1, "attribute1":[[4,157],[5,63],[6,626]], "target2":"", "attribute2":[]},
	{"id":1008019, "pokedex_level":19, "levelmax":24, "pokedex_id":1008, "hero_id":[[10007,4],[10023,4],[10049,4],[10042,4]], "consume":[[2,2,20000],[201,432004,44]], "achievement_point":0, "target1":1, "attribute1":[[4,170],[5,68],[6,680]], "target2":"", "attribute2":[]},
	{"id":1008020, "pokedex_level":20, "levelmax":24, "pokedex_id":1008, "hero_id":[[10007,4],[10023,4],[10049,4],[10042,4]], "consume":[[2,2,20000],[201,432004,44]], "achievement_point":0, "target1":1, "attribute1":[[4,184],[5,73],[6,734]], "target2":"", "attribute2":[]},
	{"id":1008021, "pokedex_level":21, "levelmax":24, "pokedex_id":1008, "hero_id":[[10007,4],[10023,4],[10049,4],[10042,4]], "consume":[[2,2,20000],[201,432004,50]], "achievement_point":0, "target1":1, "attribute1":[[4,197],[5,79],[6,788]], "target2":"", "attribute2":[]},
	{"id":1008022, "pokedex_level":22, "levelmax":24, "pokedex_id":1008, "hero_id":[[10007,4],[10023,4],[10049,4],[10042,4]], "consume":[[2,2,20000],[201,432004,50]], "achievement_point":0, "target1":1, "attribute1":[[4,211],[5,84],[6,842]], "target2":"", "attribute2":[]},
	{"id":1008023, "pokedex_level":23, "levelmax":24, "pokedex_id":1008, "hero_id":[[10007,4],[10023,4],[10049,4],[10042,4]], "consume":[[2,2,20000],[201,432004,56]], "achievement_point":0, "target1":1, "attribute1":[[4,224],[5,90],[6,896]], "target2":"", "attribute2":[]},
	{"id":1008024, "pokedex_level":24, "levelmax":24, "pokedex_id":1008, "hero_id":[[10007,4],[10023,4],[10049,4],[10042,4]], "consume":[[2,2,100000],[201,432004,56]], "achievement_point":28, "target1":1, "attribute1":[[4,247],[5,99],[6,986]], "target2":"", "attribute2":[]},
	{"id":1008025, "pokedex_level":25, "levelmax":30, "pokedex_id":1008, "hero_id":[[10007,5],[10023,5],[10049,5],[10042,5]], "consume":[[2,2,50000],[201,432004,70]], "achievement_point":0, "target1":1, "attribute1":[[4,265],[5,106],[6,1060]], "target2":"", "attribute2":[]},
	{"id":1008026, "pokedex_level":26, "levelmax":30, "pokedex_id":1008, "hero_id":[[10007,5],[10023,5],[10049,5],[10042,5]], "consume":[[2,2,50000],[201,432004,70]], "achievement_point":0, "target1":1, "attribute1":[[4,283],[5,113],[6,1133]], "target2":"", "attribute2":[]},
	{"id":1008027, "pokedex_level":27, "levelmax":30, "pokedex_id":1008, "hero_id":[[10007,5],[10023,5],[10049,5],[10042,5]], "consume":[[2,2,50000],[201,432004,80]], "achievement_point":0, "target1":1, "attribute1":[[4,302],[5,121],[6,1207]], "target2":"", "attribute2":[]},
	{"id":1008028, "pokedex_level":28, "levelmax":30, "pokedex_id":1008, "hero_id":[[10007,5],[10023,5],[10049,5],[10042,5]], "consume":[[2,2,50000],[201,432004,80]], "achievement_point":0, "target1":1, "attribute1":[[4,320],[5,128],[6,1280]], "target2":"", "attribute2":[]},
	{"id":1008029, "pokedex_level":29, "levelmax":30, "pokedex_id":1008, "hero_id":[[10007,5],[10023,5],[10049,5],[10042,5]], "consume":[[2,2,50000],[201,432004,100]], "achievement_point":0, "target1":1, "attribute1":[[4,338],[5,135],[6,1354]], "target2":"", "attribute2":[]},
	{"id":1008030, "pokedex_level":30, "levelmax":30, "pokedex_id":1008, "hero_id":[[10007,5],[10023,5],[10049,5],[10042,5]], "consume":[[2,2,200000],[201,432004,100]], "achievement_point":28, "target1":1, "attribute1":[[4,369],[5,148],[6,1476]], "target2":"", "attribute2":[]},
	{"id":1009000, "pokedex_level":0, "levelmax":0, "pokedex_id":1009, "hero_id":[[10002,1],[10013,1],[10036,1],[10029,1]], "consume":[], "achievement_point":40, "target1":3, "attribute1":[[4,15],[5,6],[6,59]], "target2":"", "attribute2":[]},
	{"id":1009001, "pokedex_level":1, "levelmax":6, "pokedex_id":1009, "hero_id":[[10002,1],[10013,1],[10036,1],[10029,1]], "consume":[[2,2,2500],[201,432004,3]], "achievement_point":0, "target1":3, "attribute1":[[4,23],[5,9],[6,94]], "target2":"", "attribute2":[]},
	{"id":1009002, "pokedex_level":2, "levelmax":6, "pokedex_id":1009, "hero_id":[[10002,1],[10013,1],[10036,1],[10029,1]], "consume":[[2,2,2500],[201,432004,3]], "achievement_point":0, "target1":3, "attribute1":[[4,32],[5,13],[6,129]], "target2":"", "attribute2":[]},
	{"id":1009003, "pokedex_level":3, "levelmax":6, "pokedex_id":1009, "hero_id":[[10002,1],[10013,1],[10036,1],[10029,1]], "consume":[[2,2,2500],[201,432004,5]], "achievement_point":0, "target1":3, "attribute1":[[4,41],[5,16],[6,164]], "target2":"", "attribute2":[]},
	{"id":1009004, "pokedex_level":4, "levelmax":6, "pokedex_id":1009, "hero_id":[[10002,1],[10013,1],[10036,1],[10029,1]], "consume":[[2,2,2500],[201,432004,5]], "achievement_point":0, "target1":3, "attribute1":[[4,50],[5,20],[6,199]], "target2":"", "attribute2":[]},
	{"id":1009005, "pokedex_level":5, "levelmax":6, "pokedex_id":1009, "hero_id":[[10002,1],[10013,1],[10036,1],[10029,1]], "consume":[[2,2,2500],[201,432004,8]], "achievement_point":0, "target1":3, "attribute1":[[4,59],[5,23],[6,235]], "target2":"", "attribute2":[]},
	{"id":1009006, "pokedex_level":6, "levelmax":6, "pokedex_id":1009, "hero_id":[[10002,1],[10013,1],[10036,1],[10029,1]], "consume":[[2,2,10000],[201,432004,8]], "achievement_point":32, "target1":3, "attribute1":[[4,73],[5,29],[6,293]], "target2":"", "attribute2":[]},
	{"id":1009007, "pokedex_level":7, "levelmax":12, "pokedex_id":1009, "hero_id":[[10002,2],[10013,2],[10036,2],[10029,2]], "consume":[[2,2,5000],[201,432004,12]], "achievement_point":0, "target1":3, "attribute1":[[4,85],[5,34],[6,339]], "target2":"", "attribute2":[]},
	{"id":1009008, "pokedex_level":8, "levelmax":12, "pokedex_id":1009, "hero_id":[[10002,2],[10013,2],[10036,2],[10029,2]], "consume":[[2,2,5000],[201,432004,12]], "achievement_point":0, "target1":3, "attribute1":[[4,96],[5,38],[6,385]], "target2":"", "attribute2":[]},
	{"id":1009009, "pokedex_level":9, "levelmax":12, "pokedex_id":1009, "hero_id":[[10002,2],[10013,2],[10036,2],[10029,2]], "consume":[[2,2,5000],[201,432004,16]], "achievement_point":0, "target1":3, "attribute1":[[4,108],[5,43],[6,431]], "target2":"", "attribute2":[]},
	{"id":1009010, "pokedex_level":10, "levelmax":12, "pokedex_id":1009, "hero_id":[[10002,2],[10013,2],[10036,2],[10029,2]], "consume":[[2,2,5000],[201,432004,16]], "achievement_point":0, "target1":3, "attribute1":[[4,119],[5,48],[6,476]], "target2":"", "attribute2":[]},
	{"id":1009011, "pokedex_level":11, "levelmax":12, "pokedex_id":1009, "hero_id":[[10002,2],[10013,2],[10036,2],[10029,2]], "consume":[[2,2,5000],[201,432004,20]], "achievement_point":0, "target1":3, "attribute1":[[4,131],[5,52],[6,522]], "target2":"", "attribute2":[]},
	{"id":1009012, "pokedex_level":12, "levelmax":12, "pokedex_id":1009, "hero_id":[[10002,2],[10013,2],[10036,2],[10029,2]], "consume":[[2,2,20000],[201,432004,20]], "achievement_point":32, "target1":3, "attribute1":[[4,150],[5,60],[6,598]], "target2":"", "attribute2":[]},
	{"id":1009013, "pokedex_level":13, "levelmax":18, "pokedex_id":1009, "hero_id":[[10002,3],[10013,3],[10036,3],[10029,3]], "consume":[[2,2,10000],[201,432004,24]], "achievement_point":0, "target1":3, "attribute1":[[4,165],[5,66],[6,662]], "target2":"", "attribute2":[]},
	{"id":1009014, "pokedex_level":14, "levelmax":18, "pokedex_id":1009, "hero_id":[[10002,3],[10013,3],[10036,3],[10029,3]], "consume":[[2,2,10000],[201,432004,24]], "achievement_point":0, "target1":3, "attribute1":[[4,181],[5,73],[6,725]], "target2":"", "attribute2":[]},
	{"id":1009015, "pokedex_level":15, "levelmax":18, "pokedex_id":1009, "hero_id":[[10002,3],[10013,3],[10036,3],[10029,3]], "consume":[[2,2,10000],[201,432004,30]], "achievement_point":0, "target1":3, "attribute1":[[4,197],[5,79],[6,788]], "target2":"", "attribute2":[]},
	{"id":1009016, "pokedex_level":16, "levelmax":18, "pokedex_id":1009, "hero_id":[[10002,3],[10013,3],[10036,3],[10029,3]], "consume":[[2,2,10000],[201,432004,30]], "achievement_point":0, "target1":3, "attribute1":[[4,213],[5,85],[6,852]], "target2":"", "attribute2":[]},
	{"id":1009017, "pokedex_level":17, "levelmax":18, "pokedex_id":1009, "hero_id":[[10002,3],[10013,3],[10036,3],[10029,3]], "consume":[[2,2,10000],[201,432004,38]], "achievement_point":0, "target1":3, "attribute1":[[4,229],[5,92],[6,915]], "target2":"", "attribute2":[]},
	{"id":1009018, "pokedex_level":18, "levelmax":18, "pokedex_id":1009, "hero_id":[[10002,3],[10013,3],[10036,3],[10029,3]], "consume":[[2,2,50000],[201,432004,38]], "achievement_point":32, "target1":3, "attribute1":[[4,255],[5,102],[6,1021]], "target2":"", "attribute2":[]},
	{"id":1009019, "pokedex_level":19, "levelmax":24, "pokedex_id":1009, "hero_id":[[10002,4],[10013,4],[10036,4],[10029,4]], "consume":[[2,2,20000],[201,432004,44]], "achievement_point":0, "target1":3, "attribute1":[[4,277],[5,111],[6,1109]], "target2":"", "attribute2":[]},
	{"id":1009020, "pokedex_level":20, "levelmax":24, "pokedex_id":1009, "hero_id":[[10002,4],[10013,4],[10036,4],[10029,4]], "consume":[[2,2,20000],[201,432004,44]], "achievement_point":0, "target1":3, "attribute1":[[4,299],[5,120],[6,1197]], "target2":"", "attribute2":[]},
	{"id":1009021, "pokedex_level":21, "levelmax":24, "pokedex_id":1009, "hero_id":[[10002,4],[10013,4],[10036,4],[10029,4]], "consume":[[2,2,20000],[201,432004,50]], "achievement_point":0, "target1":3, "attribute1":[[4,321],[5,128],[6,1285]], "target2":"", "attribute2":[]},
	{"id":1009022, "pokedex_level":22, "levelmax":24, "pokedex_id":1009, "hero_id":[[10002,4],[10013,4],[10036,4],[10029,4]], "consume":[[2,2,20000],[201,432004,50]], "achievement_point":0, "target1":3, "attribute1":[[4,343],[5,137],[6,1373]], "target2":"", "attribute2":[]},
	{"id":1009023, "pokedex_level":23, "levelmax":24, "pokedex_id":1009, "hero_id":[[10002,4],[10013,4],[10036,4],[10029,4]], "consume":[[2,2,20000],[201,432004,56]], "achievement_point":0, "target1":3, "attribute1":[[4,365],[5,146],[6,1461]], "target2":"", "attribute2":[]},
	{"id":1009024, "pokedex_level":24, "levelmax":24, "pokedex_id":1009, "hero_id":[[10002,4],[10013,4],[10036,4],[10029,4]], "consume":[[2,2,100000],[201,432004,56]], "achievement_point":32, "target1":3, "attribute1":[[4,402],[5,161],[6,1607]], "target2":"", "attribute2":[]},
	{"id":1009025, "pokedex_level":25, "levelmax":30, "pokedex_id":1009, "hero_id":[[10002,5],[10013,5],[10036,5],[10029,5]], "consume":[[2,2,50000],[201,432004,70]], "achievement_point":0, "target1":3, "attribute1":[[4,432],[5,173],[6,1727]], "target2":"", "attribute2":[]},
	{"id":1009026, "pokedex_level":26, "levelmax":30, "pokedex_id":1009, "hero_id":[[10002,5],[10013,5],[10036,5],[10029,5]], "consume":[[2,2,50000],[201,432004,70]], "achievement_point":0, "target1":3, "attribute1":[[4,462],[5,185],[6,1847]], "target2":"", "attribute2":[]},
	{"id":1009027, "pokedex_level":27, "levelmax":30, "pokedex_id":1009, "hero_id":[[10002,5],[10013,5],[10036,5],[10029,5]], "consume":[[2,2,50000],[201,432004,80]], "achievement_point":0, "target1":3, "attribute1":[[4,492],[5,197],[6,1967]], "target2":"", "attribute2":[]},
	{"id":1009028, "pokedex_level":28, "levelmax":30, "pokedex_id":1009, "hero_id":[[10002,5],[10013,5],[10036,5],[10029,5]], "consume":[[2,2,50000],[201,432004,80]], "achievement_point":0, "target1":3, "attribute1":[[4,522],[5,209],[6,2086]], "target2":"", "attribute2":[]},
	{"id":1009029, "pokedex_level":29, "levelmax":30, "pokedex_id":1009, "hero_id":[[10002,5],[10013,5],[10036,5],[10029,5]], "consume":[[2,2,50000],[201,432004,100]], "achievement_point":0, "target1":3, "attribute1":[[4,551],[5,221],[6,2206]], "target2":"", "attribute2":[]},
	{"id":1009030, "pokedex_level":30, "levelmax":30, "pokedex_id":1009, "hero_id":[[10002,5],[10013,5],[10036,5],[10029,5]], "consume":[[2,2,200000],[201,432004,100]], "achievement_point":32, "target1":3, "attribute1":[[4,601],[5,241],[6,2405]], "target2":"", "attribute2":[]},
	{"id":1010000, "pokedex_level":0, "levelmax":0, "pokedex_id":1010, "hero_id":[[10027,1],[10026,1],[10019,1],[10005,1]], "consume":[], "achievement_point":40, "target1":2, "attribute1":[[4,15],[5,6],[6,59]], "target2":"", "attribute2":[]},
	{"id":1010001, "pokedex_level":1, "levelmax":6, "pokedex_id":1010, "hero_id":[[10027,1],[10026,1],[10019,1],[10005,1]], "consume":[[2,2,2500],[201,432004,3]], "achievement_point":0, "target1":2, "attribute1":[[4,23],[5,9],[6,94]], "target2":"", "attribute2":[]},
	{"id":1010002, "pokedex_level":2, "levelmax":6, "pokedex_id":1010, "hero_id":[[10027,1],[10026,1],[10019,1],[10005,1]], "consume":[[2,2,2500],[201,432004,3]], "achievement_point":0, "target1":2, "attribute1":[[4,32],[5,13],[6,129]], "target2":"", "attribute2":[]},
	{"id":1010003, "pokedex_level":3, "levelmax":6, "pokedex_id":1010, "hero_id":[[10027,1],[10026,1],[10019,1],[10005,1]], "consume":[[2,2,2500],[201,432004,5]], "achievement_point":0, "target1":2, "attribute1":[[4,41],[5,16],[6,164]], "target2":"", "attribute2":[]},
	{"id":1010004, "pokedex_level":4, "levelmax":6, "pokedex_id":1010, "hero_id":[[10027,1],[10026,1],[10019,1],[10005,1]], "consume":[[2,2,2500],[201,432004,5]], "achievement_point":0, "target1":2, "attribute1":[[4,50],[5,20],[6,199]], "target2":"", "attribute2":[]},
	{"id":1010005, "pokedex_level":5, "levelmax":6, "pokedex_id":1010, "hero_id":[[10027,1],[10026,1],[10019,1],[10005,1]], "consume":[[2,2,2500],[201,432004,8]], "achievement_point":0, "target1":2, "attribute1":[[4,59],[5,23],[6,235]], "target2":"", "attribute2":[]},
	{"id":1010006, "pokedex_level":6, "levelmax":6, "pokedex_id":1010, "hero_id":[[10027,1],[10026,1],[10019,1],[10005,1]], "consume":[[2,2,10000],[201,432004,8]], "achievement_point":32, "target1":2, "attribute1":[[4,73],[5,29],[6,293]], "target2":"", "attribute2":[]},
	{"id":1010007, "pokedex_level":7, "levelmax":12, "pokedex_id":1010, "hero_id":[[10027,2],[10026,2],[10019,2],[10005,2]], "consume":[[2,2,5000],[201,432004,12]], "achievement_point":0, "target1":2, "attribute1":[[4,85],[5,34],[6,339]], "target2":"", "attribute2":[]},
	{"id":1010008, "pokedex_level":8, "levelmax":12, "pokedex_id":1010, "hero_id":[[10027,2],[10026,2],[10019,2],[10005,2]], "consume":[[2,2,5000],[201,432004,12]], "achievement_point":0, "target1":2, "attribute1":[[4,96],[5,38],[6,385]], "target2":"", "attribute2":[]},
	{"id":1010009, "pokedex_level":9, "levelmax":12, "pokedex_id":1010, "hero_id":[[10027,2],[10026,2],[10019,2],[10005,2]], "consume":[[2,2,5000],[201,432004,16]], "achievement_point":0, "target1":2, "attribute1":[[4,108],[5,43],[6,431]], "target2":"", "attribute2":[]},
	{"id":1010010, "pokedex_level":10, "levelmax":12, "pokedex_id":1010, "hero_id":[[10027,2],[10026,2],[10019,2],[10005,2]], "consume":[[2,2,5000],[201,432004,16]], "achievement_point":0, "target1":2, "attribute1":[[4,119],[5,48],[6,476]], "target2":"", "attribute2":[]},
	{"id":1010011, "pokedex_level":11, "levelmax":12, "pokedex_id":1010, "hero_id":[[10027,2],[10026,2],[10019,2],[10005,2]], "consume":[[2,2,5000],[201,432004,20]], "achievement_point":0, "target1":2, "attribute1":[[4,131],[5,52],[6,522]], "target2":"", "attribute2":[]},
	{"id":1010012, "pokedex_level":12, "levelmax":12, "pokedex_id":1010, "hero_id":[[10027,2],[10026,2],[10019,2],[10005,2]], "consume":[[2,2,20000],[201,432004,20]], "achievement_point":32, "target1":2, "attribute1":[[4,150],[5,60],[6,598]], "target2":"", "attribute2":[]},
	{"id":1010013, "pokedex_level":13, "levelmax":18, "pokedex_id":1010, "hero_id":[[10027,3],[10026,3],[10019,3],[10005,3]], "consume":[[2,2,10000],[201,432004,24]], "achievement_point":0, "target1":2, "attribute1":[[4,165],[5,66],[6,662]], "target2":"", "attribute2":[]},
	{"id":1010014, "pokedex_level":14, "levelmax":18, "pokedex_id":1010, "hero_id":[[10027,3],[10026,3],[10019,3],[10005,3]], "consume":[[2,2,10000],[201,432004,24]], "achievement_point":0, "target1":2, "attribute1":[[4,181],[5,73],[6,725]], "target2":"", "attribute2":[]},
	{"id":1010015, "pokedex_level":15, "levelmax":18, "pokedex_id":1010, "hero_id":[[10027,3],[10026,3],[10019,3],[10005,3]], "consume":[[2,2,10000],[201,432004,30]], "achievement_point":0, "target1":2, "attribute1":[[4,197],[5,79],[6,788]], "target2":"", "attribute2":[]},
	{"id":1010016, "pokedex_level":16, "levelmax":18, "pokedex_id":1010, "hero_id":[[10027,3],[10026,3],[10019,3],[10005,3]], "consume":[[2,2,10000],[201,432004,30]], "achievement_point":0, "target1":2, "attribute1":[[4,213],[5,85],[6,852]], "target2":"", "attribute2":[]},
	{"id":1010017, "pokedex_level":17, "levelmax":18, "pokedex_id":1010, "hero_id":[[10027,3],[10026,3],[10019,3],[10005,3]], "consume":[[2,2,10000],[201,432004,38]], "achievement_point":0, "target1":2, "attribute1":[[4,229],[5,92],[6,915]], "target2":"", "attribute2":[]},
	{"id":1010018, "pokedex_level":18, "levelmax":18, "pokedex_id":1010, "hero_id":[[10027,3],[10026,3],[10019,3],[10005,3]], "consume":[[2,2,50000],[201,432004,38]], "achievement_point":32, "target1":2, "attribute1":[[4,255],[5,102],[6,1021]], "target2":"", "attribute2":[]},
	{"id":1010019, "pokedex_level":19, "levelmax":24, "pokedex_id":1010, "hero_id":[[10027,4],[10026,4],[10019,4],[10005,4]], "consume":[[2,2,20000],[201,432004,44]], "achievement_point":0, "target1":2, "attribute1":[[4,277],[5,111],[6,1109]], "target2":"", "attribute2":[]},
	{"id":1010020, "pokedex_level":20, "levelmax":24, "pokedex_id":1010, "hero_id":[[10027,4],[10026,4],[10019,4],[10005,4]], "consume":[[2,2,20000],[201,432004,44]], "achievement_point":0, "target1":2, "attribute1":[[4,299],[5,120],[6,1197]], "target2":"", "attribute2":[]},
	{"id":1010021, "pokedex_level":21, "levelmax":24, "pokedex_id":1010, "hero_id":[[10027,4],[10026,4],[10019,4],[10005,4]], "consume":[[2,2,20000],[201,432004,50]], "achievement_point":0, "target1":2, "attribute1":[[4,321],[5,128],[6,1285]], "target2":"", "attribute2":[]},
	{"id":1010022, "pokedex_level":22, "levelmax":24, "pokedex_id":1010, "hero_id":[[10027,4],[10026,4],[10019,4],[10005,4]], "consume":[[2,2,20000],[201,432004,50]], "achievement_point":0, "target1":2, "attribute1":[[4,343],[5,137],[6,1373]], "target2":"", "attribute2":[]},
	{"id":1010023, "pokedex_level":23, "levelmax":24, "pokedex_id":1010, "hero_id":[[10027,4],[10026,4],[10019,4],[10005,4]], "consume":[[2,2,20000],[201,432004,56]], "achievement_point":0, "target1":2, "attribute1":[[4,365],[5,146],[6,1461]], "target2":"", "attribute2":[]},
	{"id":1010024, "pokedex_level":24, "levelmax":24, "pokedex_id":1010, "hero_id":[[10027,4],[10026,4],[10019,4],[10005,4]], "consume":[[2,2,100000],[201,432004,56]], "achievement_point":32, "target1":2, "attribute1":[[4,402],[5,161],[6,1607]], "target2":"", "attribute2":[]},
	{"id":1010025, "pokedex_level":25, "levelmax":30, "pokedex_id":1010, "hero_id":[[10027,5],[10026,5],[10019,5],[10005,5]], "consume":[[2,2,50000],[201,432004,70]], "achievement_point":0, "target1":2, "attribute1":[[4,432],[5,173],[6,1727]], "target2":"", "attribute2":[]},
	{"id":1010026, "pokedex_level":26, "levelmax":30, "pokedex_id":1010, "hero_id":[[10027,5],[10026,5],[10019,5],[10005,5]], "consume":[[2,2,50000],[201,432004,70]], "achievement_point":0, "target1":2, "attribute1":[[4,462],[5,185],[6,1847]], "target2":"", "attribute2":[]},
	{"id":1010027, "pokedex_level":27, "levelmax":30, "pokedex_id":1010, "hero_id":[[10027,5],[10026,5],[10019,5],[10005,5]], "consume":[[2,2,50000],[201,432004,80]], "achievement_point":0, "target1":2, "attribute1":[[4,492],[5,197],[6,1967]], "target2":"", "attribute2":[]},
	{"id":1010028, "pokedex_level":28, "levelmax":30, "pokedex_id":1010, "hero_id":[[10027,5],[10026,5],[10019,5],[10005,5]], "consume":[[2,2,50000],[201,432004,80]], "achievement_point":0, "target1":2, "attribute1":[[4,522],[5,209],[6,2086]], "target2":"", "attribute2":[]},
	{"id":1010029, "pokedex_level":29, "levelmax":30, "pokedex_id":1010, "hero_id":[[10027,5],[10026,5],[10019,5],[10005,5]], "consume":[[2,2,50000],[201,432004,100]], "achievement_point":0, "target1":2, "attribute1":[[4,551],[5,221],[6,2206]], "target2":"", "attribute2":[]},
	{"id":1010030, "pokedex_level":30, "levelmax":30, "pokedex_id":1010, "hero_id":[[10027,5],[10026,5],[10019,5],[10005,5]], "consume":[[2,2,200000],[201,432004,100]], "achievement_point":32, "target1":2, "attribute1":[[4,601],[5,241],[6,2405]], "target2":"", "attribute2":[]},
	{"id":1011000, "pokedex_level":0, "levelmax":0, "pokedex_id":1011, "hero_id":[[10007,1],[10039,1],[10043,1],[10012,1]], "consume":[], "achievement_point":40, "target1":4, "attribute1":[[4,15],[5,6],[6,59]], "target2":"", "attribute2":[]},
	{"id":1011001, "pokedex_level":1, "levelmax":6, "pokedex_id":1011, "hero_id":[[10007,1],[10039,1],[10043,1],[10012,1]], "consume":[[2,2,2500],[201,432004,3]], "achievement_point":0, "target1":4, "attribute1":[[4,23],[5,9],[6,94]], "target2":"", "attribute2":[]},
	{"id":1011002, "pokedex_level":2, "levelmax":6, "pokedex_id":1011, "hero_id":[[10007,1],[10039,1],[10043,1],[10012,1]], "consume":[[2,2,2500],[201,432004,3]], "achievement_point":0, "target1":4, "attribute1":[[4,32],[5,13],[6,129]], "target2":"", "attribute2":[]},
	{"id":1011003, "pokedex_level":3, "levelmax":6, "pokedex_id":1011, "hero_id":[[10007,1],[10039,1],[10043,1],[10012,1]], "consume":[[2,2,2500],[201,432004,5]], "achievement_point":0, "target1":4, "attribute1":[[4,41],[5,16],[6,164]], "target2":"", "attribute2":[]},
	{"id":1011004, "pokedex_level":4, "levelmax":6, "pokedex_id":1011, "hero_id":[[10007,1],[10039,1],[10043,1],[10012,1]], "consume":[[2,2,2500],[201,432004,5]], "achievement_point":0, "target1":4, "attribute1":[[4,50],[5,20],[6,199]], "target2":"", "attribute2":[]},
	{"id":1011005, "pokedex_level":5, "levelmax":6, "pokedex_id":1011, "hero_id":[[10007,1],[10039,1],[10043,1],[10012,1]], "consume":[[2,2,2500],[201,432004,8]], "achievement_point":0, "target1":4, "attribute1":[[4,59],[5,23],[6,235]], "target2":"", "attribute2":[]},
	{"id":1011006, "pokedex_level":6, "levelmax":6, "pokedex_id":1011, "hero_id":[[10007,1],[10039,1],[10043,1],[10012,1]], "consume":[[2,2,10000],[201,432004,8]], "achievement_point":32, "target1":4, "attribute1":[[4,73],[5,29],[6,293]], "target2":"", "attribute2":[]},
	{"id":1011007, "pokedex_level":7, "levelmax":12, "pokedex_id":1011, "hero_id":[[10007,2],[10039,2],[10043,2],[10012,2]], "consume":[[2,2,5000],[201,432004,12]], "achievement_point":0, "target1":4, "attribute1":[[4,85],[5,34],[6,339]], "target2":"", "attribute2":[]},
	{"id":1011008, "pokedex_level":8, "levelmax":12, "pokedex_id":1011, "hero_id":[[10007,2],[10039,2],[10043,2],[10012,2]], "consume":[[2,2,5000],[201,432004,12]], "achievement_point":0, "target1":4, "attribute1":[[4,96],[5,38],[6,385]], "target2":"", "attribute2":[]},
	{"id":1011009, "pokedex_level":9, "levelmax":12, "pokedex_id":1011, "hero_id":[[10007,2],[10039,2],[10043,2],[10012,2]], "consume":[[2,2,5000],[201,432004,16]], "achievement_point":0, "target1":4, "attribute1":[[4,108],[5,43],[6,431]], "target2":"", "attribute2":[]},
	{"id":1011010, "pokedex_level":10, "levelmax":12, "pokedex_id":1011, "hero_id":[[10007,2],[10039,2],[10043,2],[10012,2]], "consume":[[2,2,5000],[201,432004,16]], "achievement_point":0, "target1":4, "attribute1":[[4,119],[5,48],[6,476]], "target2":"", "attribute2":[]},
	{"id":1011011, "pokedex_level":11, "levelmax":12, "pokedex_id":1011, "hero_id":[[10007,2],[10039,2],[10043,2],[10012,2]], "consume":[[2,2,5000],[201,432004,20]], "achievement_point":0, "target1":4, "attribute1":[[4,131],[5,52],[6,522]], "target2":"", "attribute2":[]},
	{"id":1011012, "pokedex_level":12, "levelmax":12, "pokedex_id":1011, "hero_id":[[10007,2],[10039,2],[10043,2],[10012,2]], "consume":[[2,2,20000],[201,432004,20]], "achievement_point":32, "target1":4, "attribute1":[[4,150],[5,60],[6,598]], "target2":"", "attribute2":[]},
	{"id":1011013, "pokedex_level":13, "levelmax":18, "pokedex_id":1011, "hero_id":[[10007,3],[10039,3],[10043,3],[10012,3]], "consume":[[2,2,10000],[201,432004,24]], "achievement_point":0, "target1":4, "attribute1":[[4,165],[5,66],[6,662]], "target2":"", "attribute2":[]},
	{"id":1011014, "pokedex_level":14, "levelmax":18, "pokedex_id":1011, "hero_id":[[10007,3],[10039,3],[10043,3],[10012,3]], "consume":[[2,2,10000],[201,432004,24]], "achievement_point":0, "target1":4, "attribute1":[[4,181],[5,73],[6,725]], "target2":"", "attribute2":[]},
	{"id":1011015, "pokedex_level":15, "levelmax":18, "pokedex_id":1011, "hero_id":[[10007,3],[10039,3],[10043,3],[10012,3]], "consume":[[2,2,10000],[201,432004,30]], "achievement_point":0, "target1":4, "attribute1":[[4,197],[5,79],[6,788]], "target2":"", "attribute2":[]},
	{"id":1011016, "pokedex_level":16, "levelmax":18, "pokedex_id":1011, "hero_id":[[10007,3],[10039,3],[10043,3],[10012,3]], "consume":[[2,2,10000],[201,432004,30]], "achievement_point":0, "target1":4, "attribute1":[[4,213],[5,85],[6,852]], "target2":"", "attribute2":[]},
	{"id":1011017, "pokedex_level":17, "levelmax":18, "pokedex_id":1011, "hero_id":[[10007,3],[10039,3],[10043,3],[10012,3]], "consume":[[2,2,10000],[201,432004,38]], "achievement_point":0, "target1":4, "attribute1":[[4,229],[5,92],[6,915]], "target2":"", "attribute2":[]},
	{"id":1011018, "pokedex_level":18, "levelmax":18, "pokedex_id":1011, "hero_id":[[10007,3],[10039,3],[10043,3],[10012,3]], "consume":[[2,2,50000],[201,432004,38]], "achievement_point":32, "target1":4, "attribute1":[[4,255],[5,102],[6,1021]], "target2":"", "attribute2":[]},
	{"id":1011019, "pokedex_level":19, "levelmax":24, "pokedex_id":1011, "hero_id":[[10007,4],[10039,4],[10043,4],[10012,4]], "consume":[[2,2,20000],[201,432004,44]], "achievement_point":0, "target1":4, "attribute1":[[4,277],[5,111],[6,1109]], "target2":"", "attribute2":[]},
	{"id":1011020, "pokedex_level":20, "levelmax":24, "pokedex_id":1011, "hero_id":[[10007,4],[10039,4],[10043,4],[10012,4]], "consume":[[2,2,20000],[201,432004,44]], "achievement_point":0, "target1":4, "attribute1":[[4,299],[5,120],[6,1197]], "target2":"", "attribute2":[]},
	{"id":1011021, "pokedex_level":21, "levelmax":24, "pokedex_id":1011, "hero_id":[[10007,4],[10039,4],[10043,4],[10012,4]], "consume":[[2,2,20000],[201,432004,50]], "achievement_point":0, "target1":4, "attribute1":[[4,321],[5,128],[6,1285]], "target2":"", "attribute2":[]},
	{"id":1011022, "pokedex_level":22, "levelmax":24, "pokedex_id":1011, "hero_id":[[10007,4],[10039,4],[10043,4],[10012,4]], "consume":[[2,2,20000],[201,432004,50]], "achievement_point":0, "target1":4, "attribute1":[[4,343],[5,137],[6,1373]], "target2":"", "attribute2":[]},
	{"id":1011023, "pokedex_level":23, "levelmax":24, "pokedex_id":1011, "hero_id":[[10007,4],[10039,4],[10043,4],[10012,4]], "consume":[[2,2,20000],[201,432004,56]], "achievement_point":0, "target1":4, "attribute1":[[4,365],[5,146],[6,1461]], "target2":"", "attribute2":[]},
	{"id":1011024, "pokedex_level":24, "levelmax":24, "pokedex_id":1011, "hero_id":[[10007,4],[10039,4],[10043,4],[10012,4]], "consume":[[2,2,100000],[201,432004,56]], "achievement_point":32, "target1":4, "attribute1":[[4,402],[5,161],[6,1607]], "target2":"", "attribute2":[]},
	{"id":1011025, "pokedex_level":25, "levelmax":30, "pokedex_id":1011, "hero_id":[[10007,5],[10039,5],[10043,5],[10012,5]], "consume":[[2,2,50000],[201,432004,70]], "achievement_point":0, "target1":4, "attribute1":[[4,432],[5,173],[6,1727]], "target2":"", "attribute2":[]},
	{"id":1011026, "pokedex_level":26, "levelmax":30, "pokedex_id":1011, "hero_id":[[10007,5],[10039,5],[10043,5],[10012,5]], "consume":[[2,2,50000],[201,432004,70]], "achievement_point":0, "target1":4, "attribute1":[[4,462],[5,185],[6,1847]], "target2":"", "attribute2":[]},
	{"id":1011027, "pokedex_level":27, "levelmax":30, "pokedex_id":1011, "hero_id":[[10007,5],[10039,5],[10043,5],[10012,5]], "consume":[[2,2,50000],[201,432004,80]], "achievement_point":0, "target1":4, "attribute1":[[4,492],[5,197],[6,1967]], "target2":"", "attribute2":[]},
	{"id":1011028, "pokedex_level":28, "levelmax":30, "pokedex_id":1011, "hero_id":[[10007,5],[10039,5],[10043,5],[10012,5]], "consume":[[2,2,50000],[201,432004,80]], "achievement_point":0, "target1":4, "attribute1":[[4,522],[5,209],[6,2086]], "target2":"", "attribute2":[]},
	{"id":1011029, "pokedex_level":29, "levelmax":30, "pokedex_id":1011, "hero_id":[[10007,5],[10039,5],[10043,5],[10012,5]], "consume":[[2,2,50000],[201,432004,100]], "achievement_point":0, "target1":4, "attribute1":[[4,551],[5,221],[6,2206]], "target2":"", "attribute2":[]},
	{"id":1011030, "pokedex_level":30, "levelmax":30, "pokedex_id":1011, "hero_id":[[10007,5],[10039,5],[10043,5],[10012,5]], "consume":[[2,2,200000],[201,432004,100]], "achievement_point":32, "target1":4, "attribute1":[[4,601],[5,241],[6,2405]], "target2":"", "attribute2":[]}
]
}
